<?xml version="1.0" encoding="utf-8"?>
<db version="3" seq_piece="50690">
  <pieces>
    <piece id="674">
      <classement>
        <version date="28/01/2019 13:33:08" value="001040.3" />
      </classement>
    </piece>
    <piece id="1027">
      <classement>
        <version date="28/01/2019 13:15:55" value="0000100.4" />
      </classement>
      <duration>180187</duration>
    </piece>
    <piece id="1715">
      <classement>
        <version date="28/01/2019 16:45:06" value="0000120.4" />
      </classement>
    </piece>
    <piece id="2597">
      <classement>
        <version date="28/01/2019 18:57:12" value="30.5" />
      </classement>
      <duration>211856</duration>
    </piece>
    <piece id="3219">
      <classement>
        <version date="28/01/2019 18:52:00" value="0000214.1" />
      </classement>
    </piece>
    <piece id="3476">
      <classement>
        <version date="28/01/2019 12:32:38" value="030.4" />
      </classement>
    </piece>
    <piece id="3839">
      <classement>
        <version date="28/01/2019 13:11:41" value="200.3" />
      </classement>
      <dates>
        <date>28/01/2019 13:12:19</date>
      </dates>
    </piece>
    <piece id="3948">
      <classement>
        <version date="28/01/2019 13:25:40" value="000145.2" />
      </classement>
    </piece>
    <piece id="4241">
      <classement>
        <version date="28/01/2019 18:39:33" value="32.1" />
      </classement>
      <dates>
        <date>28/01/2019 18:39:20</date>
      </dates>
    </piece>
    <piece id="5316">
      <classement>
        <version date="28/01/2019 15:47:10" value="143.3" />
      </classement>
      <duration>289587</duration>
    </piece>
    <piece id="5722">
      <classement>
        <version date="28/01/2019 18:54:09" value="0000000005.2" />
      </classement>
      <disabled />
    </piece>
    <piece id="5752">
      <classement>
        <version date="28/01/2019 17:38:38" value="00000023.2" />
      </classement>
    </piece>
    <piece id="5967">
      <classement>
        <version date="28/01/2019 16:53:35" value="00135.3" />
      </classement>
    </piece>
    <piece id="6409">
      <classement>
        <version date="28/01/2019 15:25:59" value="0000152.1" />
      </classement>
    </piece>
    <piece id="6590">
      <classement>
        <version date="28/01/2019 16:09:00" value="0000000010.3" />
      </classement>
      <disabled />
    </piece>
    <piece id="6601">
      <classement>
        <version date="28/01/2019 14:45:53" value="000000000234.3" />
      </classement>
    </piece>
    <piece id="6770">
      <classement>
        <version date="28/01/2019 15:12:08" value="0000000005.4" />
      </classement>
      <disabled />
    </piece>
    <piece id="7012">
      <classement>
        <version date="28/01/2019 13:29:13" value="0000222.1" />
      </classement>
    </piece>
    <piece id="7189">
      <classement>
        <version date="28/01/2019 18:31:54" value="115.3" />
      </classement>
    </piece>
    <piece id="7455">
      <classement>
        <version date="28/01/2019 18:49:49" value="000410.4" />
      </classement>
    </piece>
    <piece id="7601">
      <classement>
        <version date="28/01/2019 13:23:04" value="0000345.3" />
      </classement>
    </piece>
    <piece id="8795">
      <classement>
        <version date="28/01/2019 13:01:20" value="000234.4" />
      </classement>
    </piece>
    <piece id="8824">
      <classement>
        <version date="28/01/2019 18:43:24" value="00000021.2" />
      </classement>
    </piece>
    <piece id="9179">
      <classement>
        <version date="28/01/2019 16:42:04" value="000504.1" />
      </classement>
    </piece>
    <piece id="9443">
      <classement>
        <version date="28/01/2019 15:59:39" value="000000044.1" />
      </classement>
    </piece>
    <piece id="9876">
      <classement>
        <version date="28/01/2019 18:44:18" value="24.2" />
      </classement>
      <duration>249838</duration>
    </piece>
    <piece id="11337">
      <classement>
        <version date="28/01/2019 14:49:21" value="000202.4" />
      </classement>
    </piece>
    <piece id="11391">
      <disabled>false</disabled>
    </piece>
    <piece id="12820">
      <classement>
        <version date="28/01/2019 12:31:34" value="000151.2" />
      </classement>
    </piece>
    <piece id="13537">
      <classement>
        <version date="28/01/2019 13:25:02" value="00000033.1" />
      </classement>
    </piece>
    <piece id="13540">
      <classement>
        <version date="28/01/2019 13:19:25" value="000000000122.4" />
      </classement>
    </piece>
    <piece id="15025">
      <classement>
        <version date="28/01/2019 14:52:51" value="0030.4" />
      </classement>
    </piece>
    <piece id="15920">
      <classement>
        <version date="28/01/2019 15:22:38" value="0000241.1" />
      </classement>
    </piece>
    <piece id="16623">
      <classement>
        <version date="28/01/2019 15:54:37" value="0000202.1" />
      </classement>
    </piece>
    <piece id="17675">
      <classement>
        <version date="28/01/2019 16:13:24" value="000055.5" />
      </classement>
    </piece>
    <piece id="17971">
      <classement>
        <version date="28/01/2019 15:14:03" value="000442.1" />
      </classement>
    </piece>
    <piece id="18389">
      <classement>
        <version date="28/01/2019 13:24:12" value="0000101.2" />
      </classement>
    </piece>
    <piece id="19469">
      <classement>
        <version date="28/01/2019 14:50:14" value="0000135.1" />
      </classement>
    </piece>
    <piece id="20201">
      <classement>
        <version date="28/01/2019 15:32:59" value="0000040.2" />
      </classement>
    </piece>
    <piece id="21061">
      <classement>
        <version date="28/01/2019 15:59:01" value="0000000035.1" />
      </classement>
    </piece>
    <piece id="21062">
      <classement>
        <version date="28/01/2019 16:06:55" value="000425.1" />
      </classement>
    </piece>
    <piece id="21205">
      <classement>
        <version date="28/01/2019 13:23:41" value="00000020.2" />
      </classement>
    </piece>
    <piece id="21712">
      <classement>
        <version date="28/01/2019 12:38:22" value="000405.1" />
      </classement>
    </piece>
    <piece id="22935">
      <classement>
        <version date="28/01/2019 13:30:09" value="001020.3" />
      </classement>
    </piece>
    <piece id="23226">
      <classement>
        <version date="28/01/2019 15:32:18" value="0000054.4" />
      </classement>
    </piece>
    <piece id="25074">
      <classement>
        <version date="28/01/2019 16:49:10" value="131.3" />
      </classement>
      <dates>
        <date>28/01/2019 16:51:36</date>
      </dates>
    </piece>
    <piece id="25206">
      <classement>
        <version date="28/01/2019 13:02:34" value="000501.1" />
      </classement>
    </piece>
    <piece id="25210">
      <classement>
        <version date="28/01/2019 15:09:10" value="010.5" />
      </classement>
    </piece>
    <piece id="25517">
      <classement>
        <version date="28/01/2019 15:47:10" value="022.4" />
      </classement>
      <dates>
        <date>28/01/2019 16:20:17</date>
      </dates>
    </piece>
    <piece id="25977">
      <classement>
        <version date="28/01/2019 18:47:25" value="000435.1" />
      </classement>
    </piece>
    <piece id="26727">
      <classement>
        <version date="28/01/2019 15:47:10" value="00125.1" />
      </classement>
    </piece>
    <piece id="27669">
      <classement>
        <version date="28/01/2019 16:04:27" value="000350.4" />
      </classement>
    </piece>
    <piece id="30609">
      <classement>
        <version date="28/01/2019 14:57:11" value="000415.1" />
      </classement>
    </piece>
    <piece id="32484">
      <classement>
        <version date="28/01/2019 14:53:39" value="0051.3" />
      </classement>
    </piece>
    <piece id="32584">
      <classement>
        <version date="28/01/2019 16:13:53" value="000000033.2" />
      </classement>
    </piece>
    <piece id="32604">
      <classement>
        <version date="28/01/2019 16:55:20" value="001001.3" />
      </classement>
    </piece>
    <piece id="32763">
      <classement>
        <version date="28/01/2019 12:36:15" value="0045.3" />
      </classement>
    </piece>
    <piece id="32768">
      <classement>
        <version date="28/01/2019 13:32:36" value="0000523.3" />
        <version date="27/06/2018 14:51:37" value="0000015.2" />
        <version date="12/06/2018 14:09:34" value="00000102.4" />
        <version date="31/05/2018 14:35:44" value="00000033.3" />
        <version date="30/05/2018 10:48:55" value="000000032.2" />
      </classement>
      <files>
        <file>Germain\Jungle - Drum&amp;Bass - Old School (compilations &amp; divers)\Morceaux en vrac excellente qualité\Pizzicato Five - The Earth Goes Around.mp3</file>
      </files>
      <dates>
        <date>28/01/2019 15:38:03</date>
      </dates>
    </piece>
    <piece id="32777">
      <classement>
        <version date="28/01/2019 15:07:35" value="0000000033.2" />
      </classement>
    </piece>
    <piece id="32779">
      <classement>
        <version date="28/01/2019 15:09:59" value="0000000025.2" />
      </classement>
    </piece>
    <piece id="32781">
      <classement>
        <version date="28/01/2019 15:06:23" value="0000000032.2" />
      </classement>
    </piece>
    <piece id="32800">
      <classement>
        <version date="28/01/2019 15:17:24" value="00000000050.1" />
      </classement>
    </piece>
    <piece id="33021">
      <classement>
        <version date="28/01/2019 18:55:19" value="000000000202.1" />
      </classement>
    </piece>
    <piece id="33112">
      <classement>
        <version date="28/01/2019 13:32:05" value="00000000122.3" />
      </classement>
    </piece>
    <piece id="33120">
      <classement>
        <version date="28/01/2019 18:33:02" value="00000000045.2" />
      </classement>
    </piece>
    <piece id="33279">
      <classement>
        <version date="28/01/2019 18:55:51" value="000000000051.3" />
      </classement>
      <disabled />
    </piece>
    <piece id="33287">
      <classement>
        <version date="28/01/2019 16:12:14" value="0000000025.4" />
      </classement>
    </piece>
    <piece id="33309">
      <classement>
        <version date="28/01/2019 15:03:46" value="00000000043.2" />
      </classement>
    </piece>
    <piece id="33367">
      <classement>
        <version date="28/01/2019 13:03:34" value="00000000042.2" />
      </classement>
    </piece>
    <piece id="33401">
      <classement>
        <version date="28/01/2019 15:14:34" value="00000000023.1" />
      </classement>
      <disabled />
    </piece>
    <piece id="33458">
      <classement>
        <version date="28/01/2019 13:33:58" value="00000000101.1" />
      </classement>
    </piece>
    <piece id="33465">
      <classement>
        <version date="28/01/2019 16:12:52" value="0000000042.3" />
      </classement>
    </piece>
    <piece id="33563">
      <classement>
        <version date="28/01/2019 15:05:47" value="0000000031.4" />
      </classement>
    </piece>
    <piece id="33746">
      <classement>
        <version date="28/01/2019 15:30:56" value="000000000323.3" />
      </classement>
    </piece>
    <piece id="33902">
      <classement>
        <version date="28/01/2019 13:06:54" value="000130.5" />
      </classement>
    </piece>
    <piece id="37600">
      <classement>
        <version date="28/01/2019 13:05:01" value="0031.4" />
      </classement>
    </piece>
    <piece id="37968">
      <classement>
        <version date="28/01/2019 16:01:03" value="0000020.5" />
      </classement>
    </piece>
    <piece id="38081">
      <classement>
        <version date="28/01/2019 14:48:35" value="0000533.3" />
      </classement>
    </piece>
    <piece id="38824">
      <classement>
        <version date="28/01/2019 15:10:48" value="0000000034.2" />
      </classement>
    </piece>
    <piece id="40062">
      <classement>
        <version date="28/01/2019 15:33:30" value="0000234.1" />
      </classement>
    </piece>
    <piece id="40237">
      <classement>
        <version date="28/01/2019 18:49:08" value="000400.4" />
      </classement>
    </piece>
    <piece id="40475">
      <dates>
        <date>28/01/2019 18:59:22</date>
      </dates>
    </piece>
    <piece id="40512">
      <classement>
        <version date="28/01/2019 18:42:18" value="000530.1" />
      </classement>
    </piece>
    <piece id="40875">
      <classement>
        <version date="28/01/2019 15:34:17" value="000320.4" />
      </classement>
    </piece>
    <piece id="41322">
      <classement>
        <version date="28/01/2019 16:43:02" value="000000000014.3" />
      </classement>
      <disabled />
    </piece>
    <piece id="41334">
      <classement>
        <version date="28/01/2019 18:54:53" value="0000043.2" />
      </classement>
    </piece>
    <piece id="41377">
      <classement>
        <version date="28/01/2019 18:52:49" value="0000355.3" />
      </classement>
    </piece>
    <piece id="41442">
      <classement>
        <version date="28/01/2019 16:58:05" value="000000000134.4" />
      </classement>
    </piece>
    <piece id="41476">
      <classement>
        <version date="28/01/2019 18:50:31" value="000000000122.3" />
      </classement>
      <disabled />
    </piece>
    <piece id="41500">
      <classement>
        <version date="28/01/2019 18:53:37" value="0000035.2" />
      </classement>
    </piece>
    <piece id="41600">
      <classement>
        <version date="28/01/2019 12:36:53" value="000000001.5" />
      </classement>
      <disabled />
    </piece>
    <piece id="41701">
      <classement>
        <version date="28/01/2019 13:21:39" value="0000000111.3" />
      </classement>
    </piece>
    <piece id="41772">
      <classement>
        <version date="28/01/2019 15:35:07" value="000000000104.3" />
      </classement>
      <disabled />
    </piece>
    <piece id="41781">
      <classement>
        <version date="28/01/2019 13:26:47" value="0000352.3" />
      </classement>
    </piece>
    <piece id="41813">
      <classement>
        <version date="28/01/2019 13:08:55" value="000000000121.3" />
      </classement>
      <disabled />
    </piece>
    <piece id="41859">
      <classement>
        <version date="28/01/2019 13:17:42" value="00000000121.3" />
      </classement>
    </piece>
    <piece id="41871">
      <classement>
        <version date="28/01/2019 16:44:23" value="0000000010.1" />
      </classement>
      <disabled />
    </piece>
    <piece id="41897">
      <classement>
        <version date="28/01/2019 16:54:44" value="000000000112.3" />
      </classement>
      <disabled />
    </piece>
    <piece id="41913">
      <classement>
        <version date="28/01/2019 16:47:35" value="000000000241.3" />
      </classement>
    </piece>
    <piece id="41914">
      <classement>
        <version date="28/01/2019 13:10:04" value="000000000120.2" />
      </classement>
    </piece>
    <piece id="41923">
      <classement>
        <version date="28/01/2019 13:14:03" value="0000045.4" />
      </classement>
    </piece>
    <piece id="41931">
      <classement>
        <version date="28/01/2019 13:07:42" value="000000000122.2" />
      </classement>
    </piece>
    <piece id="41948">
      <classement>
        <version date="28/01/2019 18:40:46" value="00000031.1" />
      </classement>
    </piece>
    <piece id="41951">
      <classement>
        <version date="28/01/2019 16:45:42" value="000000000123.1" />
      </classement>
    </piece>
    <piece id="41953">
      <classement>
        <version date="28/01/2019 18:34:59" value="000000034.2" />
      </classement>
    </piece>
    <piece id="41955">
      <classement>
        <version date="28/01/2019 13:17:09" value="0000051.4" />
      </classement>
    </piece>
    <piece id="42003">
      <classement>
        <version date="28/01/2019 13:13:11" value="000000000200.3" />
      </classement>
    </piece>
    <piece id="42005">
      <classement>
        <version date="28/01/2019 13:16:42" value="0000034.2" />
      </classement>
    </piece>
    <piece id="42037">
      <classement>
        <version date="28/01/2019 13:26:11" value="00000000022.2" />
      </classement>
      <disabled />
    </piece>
    <piece id="42535">
      <classement>
        <version date="28/01/2019 17:37:32" value="000000000143.3" />
      </classement>
      <disabled />
    </piece>
    <piece id="42780">
      <classement>
        <version date="28/01/2019 13:22:27" value="00000030.1" />
      </classement>
    </piece>
    <piece id="42881">
      <classement>
        <version date="28/01/2019 18:33:46" value="00000000124.3" />
      </classement>
    </piece>
    <piece id="42945">
      <classement>
        <version date="28/01/2019 18:48:12" value="00000000034.5" />
      </classement>
    </piece>
    <piece id="43519">
      <classement>
        <version date="28/01/2019 15:27:10" value="000000000131.3" />
      </classement>
      <disabled />
    </piece>
    <piece id="43839">
      <classement>
        <version date="28/01/2019 15:18:20" value="000511.1" />
      </classement>
    </piece>
    <piece id="44176">
      <classement>
        <version date="28/01/2019 13:04:10" value="000000000111.3" />
      </classement>
      <disabled />
    </piece>
    <piece id="44177">
      <classement>
        <version date="28/01/2019 14:52:11" value="000000002.0" />
      </classement>
      <disabled />
    </piece>
    <piece id="44183">
      <classement>
        <version date="28/01/2019 13:31:34" value="0000000005.1" />
      </classement>
      <disabled />
    </piece>
    <piece id="44281">
      <classement>
        <version date="28/01/2019 18:51:16" value="00000000052.1" />
      </classement>
    </piece>
    <piece id="44517">
      <classement>
        <version date="28/01/2019 16:11:33" value="0000000035.4" />
      </classement>
    </piece>
    <piece id="45341">
      <classement>
        <version date="28/01/2019 16:05:22" value="000153.1" />
      </classement>
    </piece>
    <piece id="45636">
      <classement>
        <version date="28/01/2019 15:57:52" value="000523.1" />
      </classement>
    </piece>
    <piece id="47603">
      <classement>
        <version date="28/01/2019 12:37:46" value="000513.1" />
      </classement>
    </piece>
    <piece id="47764">
      <classement>
        <version date="28/01/2019 12:35:29" value="000503.1" />
      </classement>
    </piece>
    <piece id="48257">
      <classement>
        <version date="28/01/2019 15:26:36" value="0000110.4" />
      </classement>
    </piece>
    <piece id="48699">
      <classement>
        <version date="28/01/2019 13:15:09" value="000000043.1" />
      </classement>
    </piece>
    <piece id="49189">
      <classement>
        <version date="28/01/2019 15:16:38" value="00114.4" />
      </classement>
      <dates>
        <date>28/01/2019 15:16:06</date>
      </dates>
    </piece>
    <piece id="50200">
      <classement>
        <version date="28/01/2019 13:05:53" value="0000213.1" />
      </classement>
    </piece>
    <piece id="50274">
      <classement>
        <version date="28/01/2019 11:31:50" value="000424.1" />
      </classement>
    </piece>
    <piece id="50288">
      <classement>
        <version date="28/01/2019 11:14:51" value="0000204.1" />
      </classement>
    </piece>
    <piece id="50304">
      <classement>
        <version date="28/01/2019 11:33:09" value="00000025.4" />
      </classement>
    </piece>
    <piece id="50313">
      <classement>
        <version date="28/01/2019 12:07:57" value="000000032.2" />
      </classement>
      <dates>
        <date>28/01/2019 12:07:31</date>
      </dates>
    </piece>
    <piece id="50318">
      <classement>
        <version date="28/01/2019 10:52:20" value="00000022.2" />
      </classement>
    </piece>
    <piece id="50324">
      <classement>
        <version date="28/01/2019 11:57:09" value="000310.4" />
      </classement>
    </piece>
    <piece id="50326">
      <classement>
        <version date="28/01/2019 12:20:32" value="000222.2" />
      </classement>
    </piece>
    <piece id="50333">
      <classement>
        <version date="28/01/2019 12:03:44" value="000340.4" />
      </classement>
    </piece>
    <piece id="50339">
      <classement>
        <version date="28/01/2019 12:24:14" value="000510.1" />
      </classement>
    </piece>
    <piece id="50344">
      <classement>
        <version date="28/01/2019 10:54:45" value="000250.4" />
      </classement>
    </piece>
    <piece id="50349">
      <classement>
        <version date="28/01/2019 11:57:49" value="000214.4" />
      </classement>
    </piece>
    <piece id="50356">
      <classement>
        <version date="28/01/2019 11:50:32" value="0000513.3" />
      </classement>
    </piece>
    <piece id="50362">
      <classement>
        <version date="28/01/2019 12:19:56" value="000150.2" />
      </classement>
    </piece>
    <piece id="50367">
      <classement>
        <version date="28/01/2019 11:11:32" value="0000335.3" />
      </classement>
    </piece>
    <piece id="50371">
      <classement>
        <version date="28/01/2019 12:00:07" value="000251.4" />
      </classement>
    </piece>
    <piece id="50375">
      <classement>
        <version date="28/01/2019 12:18:55" value="000500.1" />
      </classement>
      <dates>
        <date>28/01/2019 12:15:56</date>
      </dates>
    </piece>
    <piece id="50380">
      <classement>
        <version date="28/01/2019 12:29:55" value="000520.1" />
      </classement>
    </piece>
    <piece id="50385">
      <classement>
        <version date="28/01/2019 11:44:00" value="0001000.3" />
      </classement>
      <dates>
        <date>28/01/2019 11:42:44</date>
        <date>28/01/2019 11:40:02</date>
      </dates>
      <duration>92000</duration>
    </piece>
    <piece id="50396">
      <classement>
        <version date="28/01/2019 10:44:15" value="000444.1" />
      </classement>
      <duration>201000</duration>
    </piece>
    <piece id="50422">
      <classement>
        <version date="28/01/2019 11:49:56" value="000000042.1" />
      </classement>
      <dates>
        <date>28/01/2019 11:47:41</date>
      </dates>
    </piece>
    <piece id="50425">
      <classement>
        <version date="28/01/2019 11:54:46" value="0000000101.3" />
      </classement>
      <dates>
        <date>28/01/2019 11:53:39</date>
      </dates>
    </piece>
    <piece id="50435">
      <classement>
        <version date="28/01/2019 11:36:15" value="00111.4" />
      </classement>
    </piece>
    <piece id="50447">
      <classement>
        <version date="28/01/2019 11:38:28" value="000432.1" />
      </classement>
      <duration>314000</duration>
    </piece>
    <piece id="50459">
      <classement>
        <version date="28/01/2019 11:41:10" value="000330.4" />
      </classement>
    </piece>
    <piece id="50470">
      <classement>
        <version date="28/01/2019 12:10:32" value="001030.3" />
      </classement>
      <duration>201000</duration>
    </piece>
    <piece id="50474">
      <classement>
        <version date="28/01/2019 12:02:08" />
      </classement>
      <dates>
        <date>28/01/2019 12:03:46</date>
        <date>28/01/2019 12:00:34</date>
        <date>28/01/2019 12:00:22</date>
        <date>28/01/2019 12:00:09</date>
      </dates>
      <disabled />
      <duration>538355</duration>
    </piece>
    <piece id="50478">
      <classement>
        <version date="28/01/2019 11:30:39" value="000300.4" />
      </classement>
    </piece>
    <piece id="50492">
      <classement>
        <version date="28/01/2019 11:13:38" value="0000125.1" />
      </classement>
      <duration>140000</duration>
    </piece>
    <piece id="50493">
      <classement>
        <version date="28/01/2019 12:30:26" value="0000032.2" />
      </classement>
      <duration>219000</duration>
    </piece>
    <piece id="50508">
      <classement>
        <version date="28/01/2019 10:49:06" value="000144.2" />
      </classement>
    </piece>
    <piece id="50528">
      <classement>
        <version date="28/01/2019 10:58:05" value="000243.4" />
      </classement>
    </piece>
    <piece id="50548">
      <classement>
        <version date="28/01/2019 10:45:31" value="000454.1" />
      </classement>
    </piece>
    <piece id="50566">
      <classement>
        <version date="28/01/2019 11:09:52" value="000253.4" />
      </classement>
      <dates>
        <date>28/01/2019 11:07:30</date>
      </dates>
    </piece>
    <piece id="50585">
      <classement>
        <version date="28/01/2019 10:47:31" value="000402.1" />
      </classement>
    </piece>
    <piece id="50599">
      <classement>
        <version date="28/01/2019 11:28:54" value="0000540.3" />
      </classement>
      <duration>184000</duration>
    </piece>
    <piece id="50613">
      <classement>
        <version date="28/01/2019 11:27:40" value="000241.4" />
      </classement>
    </piece>
    <piece id="50627">
      <classement>
        <version date="28/01/2019 11:08:40" value="0000451.3" />
      </classement>
      <dates>
        <date>28/01/2019 11:04:17</date>
      </dates>
      <duration>229000</duration>
    </piece>
    <piece id="50647">
      <classement>
        <version date="28/01/2019 10:55:31" value="000412.3" />
      </classement>
      <duration>134000</duration>
    </piece>
    <piece id="50669">
      <classement>
        <version date="28/01/2019 10:50:22" value="001010.3" />
      </classement>
    </piece>
    <piece id="50682">
      <classement>
        <version date="28/01/2019 10:46:27" value="0000441.3" />
      </classement>
      <duration>243000</duration>
    </piece>
    <piece id="44362" deleted="true" />
  </pieces>
</db>
