<?xml version="1.0" encoding="utf-8"?>
<db version="3" seq_piece="43679">
  <pieces>
    <piece id="2186">
      <classement>
        <version date="16/05/2018 17:38:28" value="000002223.2" />
      </classement>
    </piece>
    <piece id="4361">
      <classement>
        <version date="15/05/2018 18:42:23" value="000003153.3" />
      </classement>
      <disabled />
    </piece>
    <piece id="4371">
      <classement>
        <version date="16/05/2018 15:09:41" value="000003134.1" />
      </classement>
    </piece>
    <piece id="4812">
      <classement>
        <version date="16/05/2018 10:37:38" value="000002043.2" />
      </classement>
      <disabled />
    </piece>
    <piece id="4901" />
    <piece id="5417">
      <classement>
        <version date="16/05/2018 19:02:00" value="000001452.2" />
      </classement>
    </piece>
    <piece id="5421">
      <classement>
        <version date="16/05/2018 17:25:13" value="000004310.1" />
      </classement>
    </piece>
    <piece id="5688">
      <classement>
        <version date="16/05/2018 11:45:28" value="000002535.5" />
      </classement>
    </piece>
    <piece id="5811">
      <classement>
        <version date="16/05/2018 18:12:21" value="000003231.3" />
      </classement>
      <disabled />
    </piece>
    <piece id="5831">
      <classement>
        <version date="16/05/2018 15:35:02" value="000001412.4" />
      </classement>
    </piece>
    <piece id="6402">
      <classement>
        <version date="15/05/2018 15:26:27" value="00000353.1" />
      </classement>
      <disabled />
    </piece>
    <piece id="6509">
      <classement>
        <version date="16/05/2018 10:43:23" value="000004023.3" />
      </classement>
      <dates>
        <date>16/05/2018 10:43:16</date>
      </dates>
    </piece>
    <piece id="6517">
      <classement>
        <version date="16/05/2018 19:00:35" value="000004114.3" />
      </classement>
    </piece>
    <piece id="6768" />
    <piece id="6950">
      <classement>
        <version date="16/05/2018 18:08:29" value="00000440.2" />
      </classement>
      <dates>
        <date>16/05/2018 18:07:12</date>
      </dates>
    </piece>
    <piece id="6984">
      <classement>
        <version date="16/05/2018 17:43:56" value="000001300.5" />
      </classement>
    </piece>
    <piece id="7228">
      <classement>
        <version date="16/05/2018 14:55:32" value="000004102.1" />
      </classement>
    </piece>
    <piece id="7242">
      <classement>
        <version date="16/05/2018 18:00:36" value="000004024.3" />
      </classement>
    </piece>
    <piece id="7385">
      <classement>
        <version date="16/05/2018 19:23:30" value="000142.1" />
      </classement>
      <dates>
        <date>16/05/2018 19:23:13</date>
      </dates>
    </piece>
    <piece id="7387">
      <classement>
        <version date="16/05/2018 19:09:27" value="000053.2" />
      </classement>
      <dates>
        <date>16/05/2018 19:08:59</date>
      </dates>
    </piece>
    <piece id="7391">
      <classement>
        <version date="16/05/2018 16:31:20" value="000003452.1" />
      </classement>
      <dates>
        <date>16/05/2018 16:30:56</date>
      </dates>
    </piece>
    <piece id="7403">
      <classement>
        <version date="16/05/2018 18:55:34" value="000004132.3" />
      </classement>
      <dates>
        <date>16/05/2018 18:55:36</date>
      </dates>
    </piece>
    <piece id="7535">
      <classement>
        <version date="16/05/2018 18:30:38" value="0000025210.1" />
      </classement>
      <dates>
        <date>16/05/2018 18:33:46</date>
      </dates>
    </piece>
    <piece id="8080">
      <classement>
        <version date="15/05/2018 17:25:03" value="00000325.5" />
      </classement>
      <disabled />
    </piece>
    <piece id="8161">
      <classement>
        <version date="16/05/2018 17:24:05" value="000004113.1" />
      </classement>
    </piece>
    <piece id="8218">
      <classement>
        <version date="16/05/2018 19:26:33" value="00000425.4" />
      </classement>
    </piece>
    <piece id="9190">
      <classement>
        <version date="15/05/2018 16:31:19" value="000002534.5" />
      </classement>
    </piece>
    <piece id="9304">
      <classement>
        <version date="15/05/2018 11:16:39" value="000003013.2" />
      </classement>
    </piece>
    <piece id="9308">
      <classement>
        <version date="16/05/2018 11:51:11" value="000003331.1" />
      </classement>
    </piece>
    <piece id="9324">
      <classement>
        <version date="16/05/2018 10:49:43" value="000003230.3" />
      </classement>
      <disabled />
    </piece>
    <piece id="9350">
      <classement>
        <version date="16/05/2018 16:12:37" value="000001434.4" />
      </classement>
    </piece>
    <piece id="9360" />
    <piece id="9387">
      <classement>
        <version date="16/05/2018 14:31:26" value="000004010.1" />
      </classement>
    </piece>
    <piece id="9624">
      <classement>
        <version date="15/05/2018 15:33:18" value="00000555.3" />
      </classement>
    </piece>
    <piece id="9625">
      <classement>
        <version date="16/05/2018 15:06:50" value="000004000.1" />
      </classement>
    </piece>
    <piece id="10233">
      <classement>
        <version date="16/05/2018 10:27:10" value="00000345.1" />
      </classement>
      <dates>
        <date>16/05/2018 10:27:16</date>
      </dates>
      <disabled />
    </piece>
    <piece id="10331">
      <classement>
        <version date="16/05/2018 18:56:57" value="000001211.5" />
        <version date="16/05/2018 17:33:38" value="000000520.5" />
      </classement>
    </piece>
    <piece id="11661">
      <classement>
        <version date="15/05/2018 15:39:06" value="000001042.4" />
      </classement>
      <disabled />
    </piece>
    <piece id="12805">
      <classement>
        <version date="16/05/2018 18:19:31" value="000001011.5" />
      </classement>
    </piece>
    <piece id="13248">
      <classement>
        <version date="16/05/2018 16:28:23" value="00000455.2" />
      </classement>
    </piece>
    <piece id="14734">
      <classement>
        <version date="15/05/2018 11:27:55" value="000002150.4" />
      </classement>
      <dates>
        <date>15/05/2018 11:26:32</date>
        <date>15/05/2018 11:20:49</date>
      </dates>
      <disabled />
    </piece>
    <piece id="14812">
      <classement>
        <version date="16/05/2018 18:11:25" value="000001005.2" />
      </classement>
      <disabled />
    </piece>
    <piece id="14813">
      <classement>
        <version date="16/05/2018 10:32:06" value="0000025242.1" />
      </classement>
    </piece>
    <piece id="15113">
      <classement>
        <version date="16/05/2018 17:26:59" value="000001551.4" />
      </classement>
    </piece>
    <piece id="15263">
      <classement>
        <version date="16/05/2018 10:28:40" value="000004002.1" />
      </classement>
    </piece>
    <piece id="15287">
      <classement>
        <version date="16/05/2018 19:22:31" value="000001120.5" />
        <version date="16/05/2018 18:28:50" value="000000540.5" />
      </classement>
      <dates>
        <date>16/05/2018 18:29:46</date>
      </dates>
    </piece>
    <piece id="15783">
      <classement>
        <version date="15/05/2018 18:24:03" value="000003122.2" />
      </classement>
    </piece>
    <piece id="15801">
      <classement>
        <version date="16/05/2018 14:33:14" value="000004044.3" />
      </classement>
    </piece>
    <piece id="15812">
      <classement>
        <version date="16/05/2018 17:39:52" value="000000525.4" />
        <version date="16/05/2018 15:31:55" value="000000425.2" />
      </classement>
      <dates>
        <date>16/05/2018 15:28:13</date>
      </dates>
      <disabled />
    </piece>
    <piece id="15815">
      <classement>
        <version date="16/05/2018 19:19:52" value="000001220.5" />
      </classement>
    </piece>
    <piece id="16183">
      <classement>
        <version date="15/05/2018 15:30:40" value="000002533.4" />
      </classement>
      <disabled />
    </piece>
    <piece id="16195">
      <classement>
        <version date="16/05/2018 15:33:32" value="000002113.2" />
      </classement>
    </piece>
    <piece id="16344">
      <classement>
        <version date="16/05/2018 15:00:20" value="000004032.3" />
      </classement>
    </piece>
    <piece id="16451">
      <classement>
        <version date="15/05/2018 16:28:29" value="000003510.1" />
      </classement>
    </piece>
    <piece id="16454">
      <classement>
        <version date="16/05/2018 16:21:47" value="000001010.5" />
      </classement>
    </piece>
    <piece id="16498">
      <classement>
        <version date="16/05/2018 11:53:42" value="000003123.2" />
      </classement>
    </piece>
    <piece id="16522">
      <classement>
        <version date="16/05/2018 14:57:19" value="00000443.2" />
      </classement>
    </piece>
    <piece id="16533">
      <classement>
        <version date="16/05/2018 17:54:21" value="000001422.4" />
        <version date="16/05/2018 15:50:45" value="000000440.5" />
      </classement>
    </piece>
    <piece id="16541">
      <classement>
        <version date="16/05/2018 17:10:01" value="000003150.1" />
      </classement>
    </piece>
    <piece id="16718">
      <classement>
        <version date="16/05/2018 17:34:59" value="0000010000.1" />
      </classement>
    </piece>
    <piece id="16734">
      <classement>
        <version date="16/05/2018 15:24:13" value="000004200.1" />
      </classement>
    </piece>
    <piece id="16799">
      <classement>
        <version date="15/05/2018 18:29:50" value="000000335.2" />
      </classement>
      <disabled />
    </piece>
    <piece id="16805">
      <classement>
        <version date="16/05/2018 18:59:42" value="000001225.2" />
      </classement>
    </piece>
    <piece id="16835">
      <classement>
        <version date="16/05/2018 10:47:36" value="00000430.2" />
      </classement>
    </piece>
    <piece id="16840">
      <classement>
        <version date="16/05/2018 16:32:49" value="000000545.4" />
      </classement>
    </piece>
    <piece id="16958">
      <classement>
        <version date="16/05/2018 10:36:22" value="000002013.2" />
      </classement>
      <disabled />
    </piece>
    <piece id="16972">
      <classement>
        <version date="15/05/2018 16:27:02" value="000002534.2" />
      </classement>
      <disabled />
    </piece>
    <piece id="17035">
      <classement>
        <version date="15/05/2018 18:47:34" value="000003050.1" />
      </classement>
    </piece>
    <piece id="17118">
      <classement>
        <version date="16/05/2018 17:19:13" value="000003404.1" />
      </classement>
    </piece>
    <piece id="17138">
      <classement>
        <version date="15/05/2018 17:26:44" value="0000025002.1" />
      </classement>
    </piece>
    <piece id="17247">
      <classement>
        <version date="16/05/2018 18:13:14" value="000004133.3" />
      </classement>
    </piece>
    <piece id="17266">
      <classement>
        <version date="15/05/2018 15:47:43" value="000002545.1" />
      </classement>
      <disabled />
    </piece>
    <piece id="17277">
      <classement>
        <version date="16/05/2018 14:50:18" value="000002003.4" />
      </classement>
    </piece>
    <piece id="17282">
      <classement>
        <version date="16/05/2018 10:39:05" value="0000030012.1" />
      </classement>
    </piece>
    <piece id="17400">
      <classement>
        <version date="15/05/2018 11:02:25" value="000003120.2" />
      </classement>
    </piece>
    <piece id="17465">
      <classement>
        <version date="16/05/2018 11:34:11" value="000003344.1" />
      </classement>
    </piece>
    <piece id="17742">
      <classement>
        <version date="16/05/2018 15:49:35" value="000004103.1" />
      </classement>
    </piece>
    <piece id="17999">
      <classement>
        <version date="16/05/2018 17:34:14" value="000001210.5" />
      </classement>
    </piece>
    <piece id="18003">
      <classement>
        <version date="16/05/2018 15:40:30" value="000002121.2" />
      </classement>
    </piece>
    <piece id="18007">
      <classement>
        <version date="16/05/2018 17:47:13" value="000002200.5" />
      </classement>
    </piece>
    <piece id="18090">
      <classement>
        <version date="16/05/2018 18:37:31" value="000004104.1" />
      </classement>
    </piece>
    <piece id="18221">
      <classement>
        <version date="16/05/2018 16:05:14" value="000003040.1" />
      </classement>
    </piece>
    <piece id="18364">
      <classement>
        <version date="16/05/2018 15:42:20" value="000001222.4" />
        <version date="16/05/2018 14:53:49" value="000000312.5" />
      </classement>
      <dates>
        <date>16/05/2018 15:43:50</date>
      </dates>
    </piece>
    <piece id="18373">
      <classement>
        <version date="16/05/2018 17:55:29" value="000001522.4" />
      </classement>
    </piece>
    <piece id="18528">
      <classement>
        <version date="15/05/2018 11:12:25" value="0000030000.3" />
      </classement>
    </piece>
    <piece id="18655">
      <classement>
        <version date="16/05/2018 11:22:18" value="0000025302.1" />
      </classement>
    </piece>
    <piece id="18660">
      <classement>
        <version date="16/05/2018 14:30:51" value="000003440.2" />
      </classement>
    </piece>
    <piece id="18661">
      <classement>
        <version date="15/05/2018 16:29:14" value="000002552.2" />
      </classement>
    </piece>
    <piece id="18708">
      <classement>
        <version date="16/05/2018 10:48:29" value="000002552.1" />
      </classement>
      <disabled />
    </piece>
    <piece id="18709">
      <classement>
        <version date="16/05/2018 10:33:28" value="000002500.2" />
      </classement>
      <disabled />
    </piece>
    <piece id="18730">
      <classement>
        <version date="16/05/2018 11:40:45" value="000002440.2" />
      </classement>
      <dates>
        <date>16/05/2018 11:39:22</date>
      </dates>
      <disabled />
    </piece>
    <piece id="18813">
      <classement>
        <version date="16/05/2018 11:35:31" value="000002023.2" />
      </classement>
      <disabled />
    </piece>
    <piece id="18820">
      <classement>
        <version date="15/05/2018 11:06:32" value="000003104.3" />
      </classement>
      <disabled />
    </piece>
    <piece id="18901">
      <classement>
        <version date="16/05/2018 17:51:34" value="000001332.4" />
      </classement>
    </piece>
    <piece id="18903">
      <classement>
        <version date="16/05/2018 14:59:15" value="000004022.3" />
      </classement>
    </piece>
    <piece id="18906">
      <classement>
        <version date="16/05/2018 15:18:12" value="00000415.2" />
      </classement>
    </piece>
    <piece id="18983">
      <classement>
        <version date="15/05/2018 18:35:33" value="000003524.3" />
      </classement>
    </piece>
    <piece id="19068">
      <classement>
        <version date="16/05/2018 10:40:13" value="000002541.2" />
      </classement>
      <disabled />
    </piece>
    <piece id="19072">
      <classement>
        <version date="15/05/2018 16:10:47" value="000003024.1" />
      </classement>
      <disabled />
    </piece>
    <piece id="19079">
      <classement>
        <version date="15/05/2018 17:14:10" value="000002220.2" />
      </classement>
      <disabled />
    </piece>
    <piece id="19131">
      <classement>
        <version date="16/05/2018 10:22:08" value="000003522.1" />
      </classement>
    </piece>
    <piece id="19281">
      <classement>
        <version date="15/05/2018 16:17:49" value="000003220.1" />
      </classement>
      <disabled />
    </piece>
    <piece id="19398">
      <classement>
        <version date="15/05/2018 17:20:35" value="0000030202.1" />
      </classement>
    </piece>
    <piece id="19400">
      <classement>
        <version date="15/05/2018 15:37:58" value="000003500.3" />
      </classement>
    </piece>
    <piece id="19421">
      <classement>
        <version date="16/05/2018 14:47:36" value="000002543.2" />
      </classement>
    </piece>
    <piece id="19502">
      <classement>
        <version date="15/05/2018 17:30:47" value="0000032000.1" />
      </classement>
    </piece>
    <piece id="19530">
      <classement>
        <version date="16/05/2018 19:12:57" value="0000021000.1" />
      </classement>
    </piece>
    <piece id="19619">
      <classement>
        <version date="16/05/2018 15:12:38" value="000004021.1" />
      </classement>
    </piece>
    <piece id="19702">
      <classement>
        <version date="16/05/2018 15:14:57" value="000001212.4" />
      </classement>
    </piece>
    <piece id="19812">
      <classement>
        <version date="15/05/2018 11:05:44" value="000003313.1" />
      </classement>
    </piece>
    <piece id="19814">
      <classement>
        <version date="15/05/2018 16:24:34" value="000002544.2" />
      </classement>
    </piece>
    <piece id="19882">
      <classement>
        <version date="16/05/2018 15:39:00" value="000002213.2" />
      </classement>
    </piece>
    <piece id="19985">
      <classement>
        <version date="15/05/2018 17:34:48" value="000002410.2" />
      </classement>
      <disabled />
    </piece>
    <piece id="20252">
      <classement>
        <version date="16/05/2018 15:58:24" value="000003145.4" />
      </classement>
    </piece>
    <piece id="20410">
      <classement>
        <version date="15/05/2018 16:16:37" value="000002542.4" />
      </classement>
    </piece>
    <piece id="20420">
      <classement>
        <version date="16/05/2018 18:48:18" value="000002525.5" />
      </classement>
    </piece>
    <piece id="20450">
      <classement>
        <version date="16/05/2018 18:58:04" value="000002012.4" />
      </classement>
    </piece>
    <piece id="20513">
      <classement>
        <version date="16/05/2018 18:14:40" value="000002011.4" />
      </classement>
    </piece>
    <piece id="20528">
      <classement>
        <version date="16/05/2018 15:03:39" value="000000505.2" />
      </classement>
      <dates>
        <date>16/05/2018 15:03:10</date>
      </dates>
      <disabled />
    </piece>
    <piece id="20575">
      <classement>
        <version date="16/05/2018 18:22:43" value="000001232.2" />
      </classement>
      <disabled />
    </piece>
    <piece id="20622">
      <classement>
        <version date="16/05/2018 15:37:09" value="000002203.2" />
      </classement>
    </piece>
    <piece id="20630">
      <classement>
        <version date="15/05/2018 15:51:16" value="000003554.3" />
      </classement>
    </piece>
    <piece id="20792">
      <classement>
        <version date="16/05/2018 16:18:02" value="000003041.2" />
      </classement>
    </piece>
    <piece id="20931">
      <classement>
        <version date="16/05/2018 15:13:49" value="000003243.1" />
      </classement>
    </piece>
    <piece id="21126">
      <classement>
        <version date="16/05/2018 18:39:15" value="0000012000.1" />
        <version date="16/05/2018 17:28:37" value="000000510.5" />
      </classement>
    </piece>
    <piece id="21217">
      <classement>
        <version date="15/05/2018 11:07:32" value="000003141.3" />
      </classement>
      <disabled />
    </piece>
    <piece id="21221">
      <classement>
        <version date="16/05/2018 11:48:49" value="000002310.2" />
      </classement>
      <disabled />
    </piece>
    <piece id="21225">
      <classement>
        <version date="15/05/2018 11:30:37" value="000003203.3" />
      </classement>
      <disabled />
    </piece>
    <piece id="21226">
      <classement>
        <version date="16/05/2018 15:48:24" value="000001322.2" />
      </classement>
    </piece>
    <piece id="21229">
      <classement>
        <version date="16/05/2018 16:22:56" value="000001020.5" />
      </classement>
    </piece>
    <piece id="21243">
      <classement>
        <version date="16/05/2018 17:21:26" value="000003434.1" />
      </classement>
    </piece>
    <piece id="21251">
      <classement>
        <version date="16/05/2018 11:02:59" value="000002525.4" />
      </classement>
    </piece>
    <piece id="21255">
      <classement>
        <version date="16/05/2018 11:42:53" value="000003151.4" />
      </classement>
    </piece>
    <piece id="21257">
      <classement>
        <version date="16/05/2018 15:53:15" value="000004220.3" />
      </classement>
    </piece>
    <piece id="21259">
      <classement>
        <version date="16/05/2018 10:41:30" value="000003324.1" />
      </classement>
    </piece>
    <piece id="21293">
      <classement>
        <version date="16/05/2018 11:46:31" value="000002510.2" />
      </classement>
      <disabled />
    </piece>
    <piece id="21316">
      <classement>
        <version date="15/05/2018 15:45:02" value="000003153.3" />
      </classement>
    </piece>
    <piece id="21323">
      <classement>
        <version date="16/05/2018 16:16:16" value="000001005.2" />
      </classement>
    </piece>
    <piece id="21331">
      <classement>
        <version date="16/05/2018 10:55:13" value="000002430.2" />
      </classement>
      <disabled />
    </piece>
    <piece id="21391">
      <classement>
        <version date="16/05/2018 19:17:10" value="000001324.2" />
        <version date="16/05/2018 15:55:21" value="000000535.4" />
      </classement>
      <disabled />
    </piece>
    <piece id="21551">
      <classement>
        <version date="15/05/2018 11:18:09" value="000003114.3" />
      </classement>
      <disabled />
    </piece>
    <piece id="21557">
      <classement>
        <version date="16/05/2018 11:52:04" value="00000331.5" />
      </classement>
      <disabled />
    </piece>
    <piece id="21638">
      <classement>
        <version date="16/05/2018 10:35:10" value="0000302.1" />
      </classement>
    </piece>
    <piece id="21689">
      <classement>
        <version date="16/05/2018 15:20:27" value="000004121.1" />
      </classement>
    </piece>
    <piece id="21692">
      <classement>
        <version date="16/05/2018 11:47:44" value="00000330.5" />
      </classement>
      <disabled />
    </piece>
    <piece id="21701">
      <classement>
        <version date="16/05/2018 18:51:43" value="000003242.2" />
      </classement>
    </piece>
    <piece id="21832">
      <classement>
        <version date="15/05/2018 15:29:14" value="00000403.3" />
      </classement>
      <disabled />
    </piece>
    <piece id="22024">
      <classement>
        <version date="16/05/2018 18:27:40" value="000001312.4" />
      </classement>
    </piece>
    <piece id="22027">
      <classement>
        <version date="16/05/2018 18:26:32" value="000001142.2" />
      </classement>
    </piece>
    <piece id="22097">
      <classement>
        <version date="16/05/2018 10:26:27" value="000003502.2" />
      </classement>
    </piece>
    <piece id="22176">
      <classement>
        <version date="15/05/2018 18:51:52" value="000002540.4" />
      </classement>
      <disabled />
    </piece>
    <piece id="22215">
      <classement>
        <version date="15/05/2018 15:34:33" value="00000333.2" />
      </classement>
      <disabled />
    </piece>
    <piece id="22281">
      <classement>
        <version date="16/05/2018 11:02:07" value="000003130.2" />
      </classement>
    </piece>
    <piece id="22729">
      <classement>
        <version date="15/05/2018 18:54:32" value="000003555.3" />
      </classement>
    </piece>
    <piece id="23065">
      <classement>
        <version date="16/05/2018 16:02:59" value="000002301.2" />
      </classement>
    </piece>
    <piece id="23067">
      <classement>
        <version date="16/05/2018 17:11:24" value="000003300.3" />
      </classement>
    </piece>
    <piece id="23227">
      <classement>
        <version date="16/05/2018 15:47:22" value="000004042.3" />
      </classement>
    </piece>
    <piece id="23262">
      <classement>
        <version date="16/05/2018 15:45:25" value="000002320.2" />
      </classement>
    </piece>
    <piece id="23264">
      <classement>
        <version date="16/05/2018 16:01:32" value="0000025032.1" />
      </classement>
    </piece>
    <piece id="23395">
      <classement>
        <version date="16/05/2018 18:45:47" value="0000020000.1" />
      </classement>
    </piece>
    <piece id="23432">
      <classement>
        <version date="16/05/2018 10:51:43" value="000002514.5" />
      </classement>
    </piece>
    <piece id="23434">
      <classement>
        <version date="16/05/2018 17:35:55" value="000003043.2" />
      </classement>
    </piece>
    <piece id="23480">
      <classement>
        <version date="15/05/2018 11:11:25" value="000002524.4" />
      </classement>
      <disabled />
    </piece>
    <piece id="23575">
      <classement>
        <version date="16/05/2018 16:29:12" value="000003221.4" />
      </classement>
    </piece>
    <piece id="23604">
      <classement>
        <version date="16/05/2018 15:11:35" value="000004013.3" />
      </classement>
    </piece>
    <piece id="23661">
      <classement>
        <version date="16/05/2018 17:17:59" value="000001000.5" />
      </classement>
    </piece>
    <piece id="23668">
      <classement>
        <version date="16/05/2018 11:58:08" value="000002053.2" />
      </classement>
      <disabled />
    </piece>
    <piece id="23706">
      <classement>
        <version date="15/05/2018 11:10:15" value="000003010.4" />
      </classement>
    </piece>
    <piece id="23710">
      <classement>
        <version date="16/05/2018 19:24:23" value="000003352.1" />
      </classement>
    </piece>
    <piece id="23752">
      <classement>
        <version date="16/05/2018 17:52:46" value="000001130.5" />
      </classement>
    </piece>
    <piece id="23784">
      <classement>
        <version date="15/05/2018 17:33:25" value="000001110.5" />
      </classement>
      <disabled />
    </piece>
    <piece id="24096">
      <classement>
        <version date="16/05/2018 15:10:17" value="000003512.1" />
      </classement>
      <dates>
        <date>16/05/2018 15:10:07</date>
      </dates>
    </piece>
    <piece id="24106">
      <classement>
        <version date="16/05/2018 11:00:12" value="000002544.4" />
      </classement>
      <disabled />
    </piece>
    <piece id="24114">
      <classement>
        <version date="16/05/2018 17:45:34" value="000004122.1" />
      </classement>
    </piece>
    <piece id="24120">
      <classement>
        <version date="16/05/2018 16:34:06" value="000003104.1" />
      </classement>
    </piece>
    <piece id="24340">
      <classement>
        <version date="16/05/2018 10:24:34" value="000003533.1" />
      </classement>
    </piece>
    <piece id="24352">
      <classement>
        <version date="15/05/2018 18:50:04" value="00000354.3" />
      </classement>
      <disabled />
    </piece>
    <piece id="24874">
      <classement>
        <version date="15/05/2018 11:03:40" value="000003031.1" />
      </classement>
      <dates>
        <date>15/05/2018 11:03:26</date>
      </dates>
      <disabled />
    </piece>
    <piece id="25000">
      <classement>
        <version date="16/05/2018 17:09:04" value="000001111.5" />
      </classement>
    </piece>
    <piece id="25053">
      <classement>
        <version date="16/05/2018 16:11:33" value="000002250.2" />
      </classement>
      <dates>
        <date>16/05/2018 16:10:38</date>
      </dates>
    </piece>
    <piece id="25260">
      <classement>
        <version date="16/05/2018 16:27:16" value="000002141.2" />
      </classement>
    </piece>
    <piece id="26967">
      <classement>
        <version date="16/05/2018 19:13:58" value="000004201.1" />
      </classement>
    </piece>
    <piece id="27093">
      <classement>
        <version date="16/05/2018 17:41:05" value="00000441.4" />
      </classement>
    </piece>
    <piece id="27174">
      <classement>
        <version date="16/05/2018 19:10:36" value="00000432.5" />
      </classement>
    </piece>
    <piece id="27406">
      <classement>
        <version date="16/05/2018 18:49:55" value="000004131.3" />
      </classement>
    </piece>
    <piece id="27586">
      <classement>
        <version date="16/05/2018 11:29:57" value="000003212.2" />
      </classement>
    </piece>
    <piece id="27605">
      <classement>
        <version date="16/05/2018 15:46:18" value="000004001.2" />
      </classement>
    </piece>
    <piece id="28140">
      <classement>
        <version date="16/05/2018 10:59:11" value="000002103.4" />
      </classement>
      <disabled />
    </piece>
    <piece id="28286">
      <classement>
        <version date="16/05/2018 19:02:59" value="000004121.2" />
      </classement>
    </piece>
    <piece id="28292">
      <classement>
        <version date="15/05/2018 16:23:41" value="0000024244.1" />
      </classement>
    </piece>
    <piece id="28301">
      <classement>
        <version date="15/05/2018 15:52:21" value="00000343.1" />
      </classement>
      <disabled />
    </piece>
    <piece id="28922">
      <classement>
        <version date="16/05/2018 15:25:46" value="000003450.1" />
      </classement>
    </piece>
    <piece id="28928">
      <classement>
        <version date="16/05/2018 10:19:59" value="000003241.1" />
      </classement>
    </piece>
    <piece id="28970">
      <classement>
        <version date="16/05/2018 15:01:34" value="000004112.3" />
      </classement>
    </piece>
    <piece id="29160">
      <classement>
        <version date="16/05/2018 14:26:45" value="000001122.4" />
      </classement>
    </piece>
    <piece id="29169">
      <classement>
        <version date="16/05/2018 17:42:19" value="000003340.1" />
      </classement>
    </piece>
    <piece id="29176">
      <classement>
        <version date="15/05/2018 15:45:48" value="000002525.2" />
      </classement>
      <disabled />
    </piece>
    <piece id="29268">
      <classement>
        <version date="15/05/2018 18:41:24" value="000003501.2" />
      </classement>
    </piece>
    <piece id="29529">
      <classement>
        <version date="16/05/2018 18:42:44" value="000001112.4" />
      </classement>
    </piece>
    <piece id="29536">
      <classement>
        <version date="16/05/2018 10:30:45" value="000000435.2" />
      </classement>
      <dates>
        <date>16/05/2018 10:30:35</date>
      </dates>
      <disabled />
    </piece>
    <piece id="29560">
      <classement>
        <version date="16/05/2018 17:17:21" value="000004012.2" />
      </classement>
    </piece>
    <piece id="30050">
      <classement>
        <version date="15/05/2018 18:57:32" value="000003511.2" />
      </classement>
    </piece>
    <piece id="30275">
      <classement>
        <version date="16/05/2018 15:59:36" value="000003152.1" />
      </classement>
    </piece>
    <piece id="30392">
      <classement>
        <version date="16/05/2018 19:21:32" value="00000450.1" />
      </classement>
    </piece>
    <piece id="30398">
      <classement>
        <version date="16/05/2018 17:20:39" value="000003550.3" />
      </classement>
    </piece>
    <piece id="30602">
      <classement>
        <version date="16/05/2018 16:04:06" value="000003043.1" />
      </classement>
    </piece>
    <piece id="30683">
      <classement>
        <version date="16/05/2018 17:29:58" value="000003142.2" />
      </classement>
    </piece>
    <piece id="30732">
      <classement>
        <version date="15/05/2018 16:25:38" value="000002532.2" />
      </classement>
      <disabled />
    </piece>
    <piece id="30767">
      <classement>
        <version date="15/05/2018 17:19:28" value="0000024402.1" />
      </classement>
    </piece>
    <piece id="30770">
      <classement>
        <version date="15/05/2018 18:38:25" value="000002535.4" />
      </classement>
      <disabled />
    </piece>
    <piece id="30846">
      <classement>
        <version date="16/05/2018 15:08:34" value="000004052.3" />
      </classement>
    </piece>
    <piece id="30848">
      <classement>
        <version date="15/05/2018 17:06:29" value="000003105.3" />
      </classement>
      <disabled />
    </piece>
    <piece id="30850">
      <classement>
        <version date="16/05/2018 11:41:58" value="000002550.4" />
      </classement>
      <disabled />
    </piece>
    <piece id="32169">
      <classement>
        <version date="16/05/2018 10:21:32" value="00000331.4" />
      </classement>
      <disabled />
    </piece>
    <piece id="32214">
      <classement>
        <version date="16/05/2018 11:55:19" value="000002553.4" />
      </classement>
      <disabled />
    </piece>
    <piece id="32909">
      <classement>
        <version date="15/05/2018 18:44:34" value="000001541.4" />
      </classement>
      <disabled />
    </piece>
    <piece id="32938">
      <classement>
        <version date="16/05/2018 18:20:42" value="000001504.4" />
      </classement>
    </piece>
    <piece id="33003">
      <classement>
        <version date="16/05/2018 16:07:17" value="000001354.2" />
      </classement>
    </piece>
    <piece id="33020">
      <classement>
        <version date="15/05/2018 17:16:03" value="000001512.2" />
      </classement>
      <dates />
      <disabled />
    </piece>
    <piece id="33026">
      <classement>
        <version date="15/05/2018 16:12:15" value="000001344.2" />
      </classement>
      <disabled />
    </piece>
    <piece id="33029">
      <classement>
        <version date="15/05/2018 11:15:34" value="000003321.3" />
      </classement>
    </piece>
    <piece id="33086">
      <classement>
        <version date="16/05/2018 19:06:27" value="000001510.5" />
      </classement>
    </piece>
    <piece id="33157">
      <classement>
        <version date="16/05/2018 17:37:25" value="000003151.1" />
      </classement>
    </piece>
    <piece id="33191">
      <classement>
        <version date="16/05/2018 18:54:51" value="000001015.2" />
        <version date="16/05/2018 16:21:06" value="000000515.4" />
      </classement>
      <dates>
        <date>16/05/2018 16:21:12</date>
      </dates>
      <disabled />
    </piece>
    <piece id="33316">
      <classement>
        <version date="15/05/2018 16:19:24" value="000000405.2" />
      </classement>
      <disabled />
    </piece>
    <piece id="33351">
      <classement>
        <version date="16/05/2018 16:25:02" value="000000414.2" />
        <version date="16/05/2018 14:36:50" value="000000345.2" />
      </classement>
      <disabled />
    </piece>
    <piece id="33377">
      <classement>
        <version date="16/05/2018 18:41:17" value="0000013200.1" />
      </classement>
    </piece>
    <piece id="33378">
      <classement>
        <version date="16/05/2018 17:47:58" value="000000445.2" />
      </classement>
      <disabled />
    </piece>
    <piece id="33379">
      <classement>
        <version date="16/05/2018 11:20:20" value="000001052.2" />
      </classement>
      <disabled />
    </piece>
    <piece id="33398">
      <classement>
        <version date="16/05/2018 18:21:41" value="000000510.5" />
      </classement>
      <disabled />
    </piece>
    <piece id="33423">
      <classement>
        <version date="16/05/2018 15:57:12" value="000002133.2" />
      </classement>
      <dates>
        <date>16/05/2018 15:56:56</date>
      </dates>
      <disabled />
    </piece>
    <piece id="33431">
      <classement>
        <version date="16/05/2018 19:29:11" value="000002111.4" />
      </classement>
    </piece>
    <piece id="33468">
      <classement>
        <version date="16/05/2018 18:15:49" value="000002311.4" />
      </classement>
    </piece>
    <piece id="33481">
      <classement>
        <version date="16/05/2018 18:35:12" value="000001105.2" />
        <version date="16/05/2018 14:52:16" value="000000505.2" />
      </classement>
    </piece>
    <piece id="33567">
      <classement>
        <version date="16/05/2018 19:04:52" value="000001020.5" />
        <version date="16/05/2018 18:01:27" value="000000530.5" />
      </classement>
      <disabled />
    </piece>
    <piece id="33568">
      <classement>
        <version date="15/05/2018 17:10:19" value="000003115.3" />
      </classement>
      <disabled />
    </piece>
    <piece id="33574">
      <classement>
        <version date="16/05/2018 18:23:59" value="000003112.2" />
      </classement>
    </piece>
    <piece id="33721">
      <classement>
        <version date="16/05/2018 14:54:54" value="000001100.5" />
      </classement>
    </piece>
    <piece id="33728">
      <classement>
        <version date="16/05/2018 17:31:12" value="000001202.4" />
      </classement>
      <disabled />
    </piece>
    <piece id="33730">
      <classement>
        <version date="16/05/2018 14:29:40" value="000001202.4" />
      </classement>
    </piece>
    <piece id="33787">
      <classement>
        <version date="16/05/2018 18:25:47" value="000002021.2" />
      </classement>
    </piece>
    <piece id="33861">
      <classement>
        <version date="16/05/2018 17:56:37" value="000001442.2" />
      </classement>
    </piece>
    <piece id="34430">
      <classement>
        <version date="16/05/2018 19:11:48" value="000001520.5" />
      </classement>
    </piece>
    <piece id="37976">
      <classement>
        <version date="16/05/2018 17:27:42" value="000001122.4" />
        <version date="16/05/2018 14:45:00" value="000000414.2" />
      </classement>
      <dates>
        <date>16/05/2018 14:41:29</date>
      </dates>
      <disabled />
    </piece>
    <piece id="38895">
      <classement>
        <version date="16/05/2018 18:47:00" value="000000345.2" />
      </classement>
      <disabled />
    </piece>
    <piece id="39253">
      <classement>
        <version date="16/05/2018 16:30:17" value="000003015.2" />
      </classement>
    </piece>
    <piece id="40569">
      <classement>
        <version date="16/05/2018 19:18:46" value="0000133.5" />
      </classement>
    </piece>
    <piece id="40604">
      <classement>
        <version date="15/05/2018 15:41:54" value="00001133.3" />
      </classement>
    </piece>
    <piece id="40605">
      <classement>
        <version date="15/05/2018 16:14:40" value="000114.1" />
      </classement>
    </piece>
    <piece id="40651">
      <classement>
        <version date="16/05/2018 19:27:25" />
      </classement>
      <disabled />
    </piece>
    <piece id="40680">
      <classement>
        <version date="16/05/2018 19:08:06" value="00041.2" />
      </classement>
    </piece>
    <piece id="40821">
      <classement>
        <version date="16/05/2018 11:28:38" value="000003044.3" />
      </classement>
      <disabled />
    </piece>
    <piece id="41060">
      <classement>
        <version date="15/05/2018 10:58:14" value="0000212.1" />
      </classement>
      <dates>
        <date>15/05/2018 10:59:53</date>
      </dates>
    </piece>
    <piece id="41061">
      <classement>
        <version date="15/05/2018 11:14:15" value="000043.5" />
      </classement>
    </piece>
    <piece id="41247">
      <classement>
        <version date="15/05/2018 17:44:38" value="000003000.4" />
      </classement>
      <dates>
        <date>15/05/2018 17:47:19</date>
        <date>15/05/2018 17:43:19</date>
        <date>15/05/2018 17:39:33</date>
      </dates>
      <disabled />
    </piece>
    <piece id="41314">
      <classement>
        <version date="15/05/2018 19:05:52" value="000002543.4" />
      </classement>
      <dates>
        <date>15/05/2018 19:02:12</date>
      </dates>
      <disabled />
    </piece>
    <piece id="41400">
      <classement>
        <version date="15/05/2018 18:33:17" value="0000025110.1" />
      </classement>
    </piece>
    <piece id="41418">
      <classement>
        <version date="16/05/2018 11:18:21" value="000002555.1" />
      </classement>
      <disabled />
    </piece>
    <piece id="41491">
      <classement>
        <version date="15/05/2018 18:55:41" value="000003050.3" />
      </classement>
      <disabled />
    </piece>
    <piece id="41526">
      <classement>
        <version date="15/05/2018 18:26:54" value="000003010.2" />
      </classement>
      <dates>
        <date>15/05/2018 18:28:49</date>
      </dates>
      <disabled />
    </piece>
    <piece id="41687">
      <classement>
        <version date="16/05/2018 11:44:42" value="000003025.1" />
      </classement>
      <disabled />
    </piece>
    <piece id="41816">
      <classement>
        <version date="16/05/2018 11:21:27" value="000003034.1" />
      </classement>
      <disabled />
    </piece>
    <piece id="41856">
      <classement>
        <version date="16/05/2018 10:45:09" value="00000332.4" />
      </classement>
      <dates>
        <date>16/05/2018 10:46:42</date>
      </dates>
      <disabled />
    </piece>
    <piece id="41939">
      <classement>
        <version date="15/05/2018 16:20:51" value="000003033.1" />
      </classement>
      <disabled />
    </piece>
    <piece id="41972">
      <classement>
        <version date="15/05/2018 15:36:14" value="000003211.1" />
      </classement>
      <disabled />
    </piece>
    <piece id="41977">
      <classement>
        <version date="16/05/2018 10:29:42" value="00000401.1" />
      </classement>
      <disabled />
    </piece>
    <piece id="41998">
      <classement>
        <version date="16/05/2018 11:59:18" value="000002520.2" />
      </classement>
      <disabled />
    </piece>
    <piece id="42102">
      <classement>
        <version date="15/05/2018 17:15:07" value="000002345.4" />
      </classement>
      <disabled />
    </piece>
    <piece id="42179">
      <classement>
        <version date="15/05/2018 16:13:34" value="000003124.3" />
      </classement>
      <disabled />
    </piece>
    <piece id="42227">
      <classement>
        <version date="16/05/2018 11:49:49" value="000002420.2" />
      </classement>
      <disabled />
    </piece>
    <piece id="42311">
      <classement>
        <version date="15/05/2018 11:08:24" value="000003431.1" />
      </classement>
    </piece>
    <piece id="42316">
      <classement>
        <version date="15/05/2018 11:33:40" value="0000203.4" />
      </classement>
    </piece>
    <piece id="42324">
      <classement>
        <version date="15/05/2018 18:22:17" value="00040.1" />
      </classement>
    </piece>
    <piece id="42325">
      <classement>
        <version date="16/05/2018 11:17:05" value="0000323.3" />
      </classement>
    </piece>
    <piece id="42440">
      <classement>
        <version date="15/05/2018 15:40:29" value="000052.2" />
      </classement>
    </piece>
    <piece id="42678">
      <classement>
        <version date="16/05/2018 11:31:16" value="000002542.4" />
      </classement>
      <disabled />
    </piece>
    <piece id="42938">
      <classement>
        <version date="15/05/2018 18:45:37" value="000003111.3" />
      </classement>
    </piece>
    <piece id="42954">
      <classement>
        <version date="15/05/2018 16:30:05" value="000002330.2" />
      </classement>
      <disabled />
    </piece>
    <piece id="42999">
      <classement>
        <version date="15/05/2018 15:54:41" value="000004111.1" />
      </classement>
    </piece>
    <piece id="43297">
      <classement>
        <version date="16/05/2018 10:23:36" value="00000344.1" />
      </classement>
      <disabled />
    </piece>
    <piece id="43351">
      <classement>
        <version date="15/05/2018 15:32:17" value="000051.4" />
      </classement>
    </piece>
    <piece id="43383">
      <classement>
        <version date="15/05/2018 17:04:25" value="000003042.3" />
      </classement>
      <disabled />
    </piece>
    <piece id="43416">
      <classement>
        <version date="15/05/2018 15:24:45" value="0000242.3" />
      </classement>
      <dates>
        <date>15/05/2018 11:36:45</date>
      </dates>
    </piece>
  </pieces>
</db>
