<?xml version="1.0" encoding="utf-8"?>
<db version="3" seq_piece="44807">
  <pieces>
    <piece id="1689">
      <classement>
        <version date="14/06/2018 18:03:01" value="000000411.2" />
      </classement>
      <disabled />
    </piece>
    <piece id="5731">
      <classement>
        <version date="14/06/2018 16:27:22" value="000000142.2" />
      </classement>
      <disabled />
    </piece>
    <piece id="9270">
      <classement>
        <version date="14/06/2018 16:46:57" value="00000102.1" />
      </classement>
      <disabled />
    </piece>
    <piece id="9371">
      <classement>
        <version date="14/06/2018 16:03:59" value="000000443.2" />
      </classement>
    </piece>
    <piece id="9385">
      <classement>
        <version date="14/06/2018 17:31:04" value="000000452.3" />
      </classement>
      <disabled />
    </piece>
    <piece id="9398">
      <classement>
        <version date="14/06/2018 16:53:44" value="000000403.1" />
      </classement>
      <disabled />
    </piece>
    <piece id="9422">
      <classement>
        <version date="14/06/2018 18:09:41" value="000000423.1" />
      </classement>
      <dates>
        <date>14/06/2018 18:09:45</date>
      </dates>
      <disabled />
    </piece>
    <piece id="9570">
      <classement>
        <version date="14/06/2018 15:02:33" value="000000502.1" />
      </classement>
      <duration>488939</duration>
    </piece>
    <piece id="9580">
      <classement>
        <version date="14/06/2018 16:29:17" value="000000454.3" />
      </classement>
      <disabled />
    </piece>
    <piece id="15301">
      <classement>
        <version date="14/06/2018 15:11:56" value="000000203.2" />
      </classement>
      <dates>
        <date>14/06/2018 15:11:39</date>
        <date>14/06/2018 15:11:08</date>
      </dates>
      <disabled />
    </piece>
    <piece id="15813">
      <classement>
        <version date="14/06/2018 18:07:06" value="000000523.3" />
      </classement>
      <disabled />
    </piece>
    <piece id="16196">
      <classement>
        <version date="14/06/2018 16:15:27" value="000000501.3" />
      </classement>
    </piece>
    <piece id="16470">
      <classement>
        <version date="14/06/2018 16:11:53" value="000000232.1" />
      </classement>
      <disabled />
    </piece>
    <piece id="16515">
      <classement>
        <version date="14/06/2018 18:13:40" value="000000210.2" />
      </classement>
      <disabled />
    </piece>
    <piece id="16531">
      <classement>
        <version date="14/06/2018 18:50:42" value="000000230.4" />
      </classement>
      <disabled />
    </piece>
    <piece id="16696">
      <classement>
        <version date="14/06/2018 16:49:22" value="00000115.3" />
      </classement>
    </piece>
    <piece id="16813">
      <classement>
        <version date="14/06/2018 17:58:51" value="000000224.4" />
      </classement>
      <disabled />
    </piece>
    <piece id="18302">
      <classement>
        <version date="14/06/2018 15:06:07" value="000000422.2" />
      </classement>
    </piece>
    <piece id="18732">
      <classement>
        <version date="14/06/2018 15:27:44" value="00000105.3" />
      </classement>
      <disabled />
    </piece>
    <piece id="19180">
      <classement>
        <version date="14/06/2018 17:55:53" value="000000542.1" />
      </classement>
    </piece>
    <piece id="19247">
      <classement>
        <version date="14/06/2018 17:34:42" value="000000511.3" />
      </classement>
      <disabled />
    </piece>
    <piece id="19302">
      <classement>
        <version date="14/06/2018 18:09:00" value="000000524.3" />
      </classement>
    </piece>
    <piece id="19305">
      <classement>
        <version date="14/06/2018 18:21:32" value="000000433.1" />
      </classement>
      <dates>
        <date>14/06/2018 18:19:21</date>
      </dates>
      <disabled />
    </piece>
    <piece id="19321">
      <classement>
        <version date="14/06/2018 16:32:31" value="000000501.3" />
      </classement>
      <disabled />
    </piece>
    <piece id="19909">
      <classement>
        <version date="14/06/2018 18:55:06" value="0000011.5" />
      </classement>
      <disabled />
    </piece>
    <piece id="19922">
      <classement>
        <version date="14/06/2018 15:26:10" value="00000104.1" />
      </classement>
    </piece>
    <piece id="20698">
      <classement>
        <version date="14/06/2018 17:44:51" value="00000103.1" />
      </classement>
      <disabled />
    </piece>
    <piece id="21167">
      <classement>
        <version date="14/06/2018 17:42:45" value="000000523.3" />
      </classement>
    </piece>
    <piece id="21655">
      <classement>
        <version date="14/06/2018 16:52:20" value="000005.1" />
      </classement>
    </piece>
    <piece id="22021">
      <classement>
        <version date="14/06/2018 18:16:18" value="0000040.1" />
      </classement>
      <dates>
        <date>14/06/2018 18:16:07</date>
      </dates>
    </piece>
    <piece id="22034">
      <classement>
        <version date="14/06/2018 16:59:59" value="000000504.3" />
      </classement>
      <disabled />
    </piece>
    <piece id="22046">
      <classement>
        <version date="14/06/2018 16:57:37" value="000000452.2" />
      </classement>
    </piece>
    <piece id="23417">
      <classement>
        <version date="14/06/2018 16:47:37" value="000000513.3" />
      </classement>
      <disabled />
    </piece>
    <piece id="24767">
      <classement>
        <version date="14/06/2018 16:44:32" value="00000055.5" />
      </classement>
    </piece>
    <piece id="26956">
      <classement>
        <version date="14/06/2018 15:33:53" value="00004.4" />
      </classement>
    </piece>
    <piece id="31528">
      <classement>
        <version date="14/06/2018 17:27:19" value="000000511.3" />
      </classement>
    </piece>
    <piece id="32483">
      <classement>
        <version date="14/06/2018 17:51:38" value="0000000453.3" />
      </classement>
      <disabled />
    </piece>
    <piece id="32589">
      <classement>
        <version date="14/06/2018 16:18:05" value="00000055.1" />
      </classement>
    </piece>
    <piece id="32595">
      <classement>
        <version date="14/06/2018 16:53:04" value="000000223.4" />
      </classement>
      <disabled />
    </piece>
    <piece id="32677">
      <classement>
        <version date="14/06/2018 17:49:43" value="0000000211.1" />
      </classement>
      <disabled />
    </piece>
    <piece id="32795">
      <classement>
        <version date="14/06/2018 16:20:55" value="00000055.4" />
      </classement>
      <dates>
        <date>14/06/2018 16:26:10</date>
      </dates>
    </piece>
    <piece id="32993">
      <classement>
        <version date="14/06/2018 14:54:32" value="000000430.4" />
      </classement>
    </piece>
    <piece id="33099">
      <classement>
        <version date="14/06/2018 16:07:39" value="000001.5" />
      </classement>
      <disabled />
    </piece>
    <piece id="33154">
      <files>
        <file>Germain\DAYS OF THE NEW\Days Of The New I\11-How Do You Know You _.mp3</file>
      </files>
    </piece>
    <piece id="33233">
      <classement>
        <version date="14/06/2018 16:05:39" value="00000000041.2" />
      </classement>
      <disabled />
    </piece>
    <piece id="33316">
      <classement>
        <version date="14/06/2018 16:56:37" value="000000450.1" />
      </classement>
    </piece>
    <piece id="33326">
      <classement>
        <version date="14/06/2018 17:41:24" value="000000512.2" />
      </classement>
    </piece>
    <piece id="33742">
      <classement>
        <version date="14/06/2018 16:48:40" value="0000011.4" />
      </classement>
      <disabled />
    </piece>
    <piece id="33753">
      <classement>
        <version date="14/06/2018 16:13:04" value="000000511.2" />
      </classement>
    </piece>
    <piece id="33754">
      <classement>
        <version date="14/06/2018 15:32:05" value="000000503.3" />
      </classement>
      <disabled />
    </piece>
    <piece id="33767">
      <classement>
        <version date="14/06/2018 15:04:59" value="00000110.1" />
      </classement>
    </piece>
    <piece id="38825">
      <classement>
        <version date="14/06/2018 16:39:23" value="0000000252.3" />
      </classement>
      <disabled />
    </piece>
    <piece id="41366">
      <classement>
        <version date="14/06/2018 14:58:06" value="0000000202.1" />
      </classement>
      <disabled />
    </piece>
    <piece id="41391">
      <classement>
        <version date="14/06/2018 18:48:50" value="00000000201.3" />
      </classement>
      <disabled />
    </piece>
    <piece id="41437">
      <classement>
        <version date="14/06/2018 15:30:47" value="000000353.1" />
      </classement>
      <disabled />
    </piece>
    <piece id="41438">
      <classement>
        <version date="14/06/2018 16:33:39" value="00000054.4" />
      </classement>
      <disabled />
    </piece>
    <piece id="41481">
      <classement>
        <version date="14/06/2018 16:10:35" value="000000513.3" />
      </classement>
    </piece>
    <piece id="41512">
      <classement>
        <version date="14/06/2018 17:40:21" value="000000433.1" />
      </classement>
    </piece>
    <piece id="41564">
      <classement>
        <version date="14/06/2018 15:29:07" value="000000215.4" />
      </classement>
      <disabled />
    </piece>
    <piece id="41654">
      <classement>
        <version date="14/06/2018 18:12:25" value="00000000210.3" />
      </classement>
      <disabled />
    </piece>
    <piece id="41754">
      <classement>
        <version date="14/06/2018 16:35:07" value="00000000154.3" />
      </classement>
      <disabled />
    </piece>
    <piece id="41828">
      <classement>
        <version date="14/06/2018 15:25:22" value="000000503.2" />
      </classement>
    </piece>
    <piece id="41914">
      <classement>
        <version date="14/06/2018 16:14:27" value="000000520.3" />
      </classement>
      <disabled />
    </piece>
    <piece id="42000">
      <classement>
        <version date="14/06/2018 16:31:23" value="00000000151.3" />
      </classement>
      <disabled />
    </piece>
    <piece id="42035">
      <classement>
        <version date="14/06/2018 16:50:16" value="0000000204.1" />
      </classement>
      <disabled />
    </piece>
    <piece id="42111">
      <classement>
        <version date="14/06/2018 17:46:08" value="000001000.1" />
      </classement>
    </piece>
    <piece id="42161">
      <classement>
        <version date="14/06/2018 18:27:32" value="00000000220.3" />
      </classement>
      <disabled />
    </piece>
    <piece id="42187">
      <classement>
        <version date="14/06/2018 17:00:58" value="000000154.2" />
      </classement>
      <disabled />
    </piece>
    <piece id="42361" />
    <piece id="43152">
      <classement>
        <version date="14/06/2018 18:04:36" value="000000201.4" />
      </classement>
      <disabled />
    </piece>
    <piece id="43267">
      <classement>
        <version date="14/06/2018 17:37:32" value="00000055.1" />
      </classement>
      <disabled />
    </piece>
    <piece id="43386">
      <classement>
        <version date="14/06/2018 14:51:58" value="000000135.2" />
      </classement>
      <dates>
        <date>14/06/2018 14:52:53</date>
      </dates>
      <disabled />
    </piece>
    <piece id="43403">
      <classement>
        <version date="14/06/2018 16:55:33" value="000000235.1" />
      </classement>
      <dates>
        <date>14/06/2018 16:55:18</date>
      </dates>
      <disabled />
    </piece>
    <piece id="43434">
      <classement>
        <version date="14/06/2018 15:10:28" value="000000343.1" />
      </classement>
      <disabled />
    </piece>
    <piece id="43609">
      <classement>
        <version date="14/06/2018 15:03:24" value="000000333.1" />
      </classement>
      <dates>
        <date>14/06/2018 15:03:26</date>
      </dates>
      <disabled />
    </piece>
    <piece id="43629">
      <classement>
        <version date="14/06/2018 16:08:56" value="000000301.1" />
      </classement>
      <dates>
        <date>14/06/2018 16:09:18</date>
      </dates>
      <disabled />
    </piece>
    <piece id="44068">
      <classement>
        <version date="14/06/2018 16:16:38" value="0000025.3" />
      </classement>
    </piece>
    <piece id="44069">
      <classement>
        <version date="14/06/2018 16:41:03" value="000010.1" />
        <version date="14/06/2018 16:38:03" value="00000000101.4" />
      </classement>
    </piece>
    <piece id="44070">
      <classement>
        <version date="14/06/2018 17:47:28" value="00000000203.3" />
      </classement>
      <disabled />
    </piece>
    <piece id="44071">
      <classement>
        <version date="14/06/2018 17:50:54" value="0000000324.3" />
      </classement>
      <disabled />
    </piece>
    <piece id="44111">
      <classement>
        <version date="14/06/2018 18:22:16" value="000000455.3" />
      </classement>
      <disabled />
    </piece>
    <piece id="44118">
      <classement>
        <version date="14/06/2018 15:08:40" value="00000054.2" />
      </classement>
      <disabled />
    </piece>
    <piece id="44124">
      <classement>
        <version date="14/06/2018 15:01:21" value="000000430.1" />
      </classement>
      <disabled />
    </piece>
    <piece id="44139">
      <classement>
        <version date="14/06/2018 16:54:47" value="0000030.3" />
      </classement>
    </piece>
    <piece id="44140">
      <classement>
        <version date="14/06/2018 16:58:59" value="000004.4" />
      </classement>
    </piece>
    <piece id="44141">
      <classement>
        <version date="14/06/2018 17:02:08" value="000000553.3" />
      </classement>
    </piece>
    <piece id="44147">
      <classement>
        <version date="14/06/2018 17:29:07" value="000000423.2" />
      </classement>
      <duration>325544</duration>
    </piece>
    <piece id="44148">
      <classement>
        <version date="14/06/2018 17:31:59" value="0000013.2" />
      </classement>
    </piece>
    <piece id="44149">
      <classement>
        <version date="14/06/2018 17:36:30" value="0000013.5" />
      </classement>
      <duration>249815</duration>
    </piece>
    <piece id="44150">
      <classement>
        <version date="14/06/2018 17:39:04" value="000005.2" />
      </classement>
      <duration>287693</duration>
    </piece>
    <piece id="44151">
      <classement>
        <version date="14/06/2018 17:54:02" value="003.3" />
        <version date="27/06/2016 08:01:48" value="05.2" />
      </classement>
      <files>
        <file>Germain\DAYS OF THE NEWS\Days Of The New I\01-Shelf In The Room.mp3</file>
      </files>
      <dates>
        <date>27/06/2016 08:03:39</date>
      </dates>
    </piece>
    <piece id="44152">
      <classement>
        <version date="14/06/2018 17:57:07" value="001.3" />
        <version date="18/07/2016 14:54:12" value="051.3" />
      </classement>
      <files>
        <file>Germain\DAYS OF THE NEWS\Days Of The New I\02-Touch, Peel and Stand.mp3</file>
      </files>
    </piece>
    <piece id="44153">
      <classement>
        <version date="14/06/2018 18:01:38" value="00.5" />
        <version date="23/09/2016 18:45:16" value="053.1" />
      </classement>
      <files>
        <file>Germain\DAYS OF THE NEWS\Days Of The New I\03-Face Of The Earth.mp3</file>
      </files>
    </piece>
    <piece id="44154">
      <classement>
        <version date="14/06/2018 18:08:18" value="002.1" />
        <version date="03/11/2016 17:18:17" value="0325.3" />
      </classement>
      <files>
        <file>Germain\DAYS OF THE NEWS\Days Of The New I\04-Solitude.mp3</file>
      </files>
    </piece>
    <piece id="44155">
      <classement>
        <version date="14/06/2018 18:11:15" value="0004.4" />
        <version date="18/01/2017 00:17:13" value="0043.2" />
      </classement>
      <files>
        <file>Germain\DAYS OF THE NEWS\Days Of The New I\05-The Down Town.mp3</file>
      </files>
    </piece>
    <piece id="44156">
      <classement>
        <version date="14/06/2018 18:17:33" value="004.3" />
        <version date="18/01/2017 08:34:58" value="0052.3" />
      </classement>
      <files>
        <file>Germain\DAYS OF THE NEWS\Days Of The New I\06-What's Left Fo Me _.mp3</file>
      </files>
    </piece>
    <piece id="44157">
      <classement>
        <version date="18/01/2017 14:06:12" value="0053.5" />
      </classement>
      <files>
        <file>Germain\DAYS OF THE NEWS\Days Of The New I\07-Freak.mp3</file>
      </files>
    </piece>
    <piece id="44158">
      <classement>
        <version date="20/01/2017 13:34:16" value="0031.4" />
      </classement>
      <files>
        <file>Germain\DAYS OF THE NEWS\Days Of The New I\08-Now.mp3</file>
      </files>
    </piece>
    <piece id="44159">
      <classement>
        <version date="20/01/2017 17:12:25" value="0032.2" />
      </classement>
      <files>
        <file>Germain\DAYS OF THE NEWS\Days Of The New I\09-Whimsical.mp3</file>
      </files>
    </piece>
    <piece id="44160">
      <classement>
        <version date="21/01/2017 17:03:53" value="0043.1" />
      </classement>
      <files>
        <file>Germain\DAYS OF THE NEWS\Days Of The New I\10-Where I Stand.mp3</file>
      </files>
    </piece>
    <piece id="44162">
      <classement>
        <version date="23/01/2017 11:05:52" value="0051.2" />
      </classement>
      <files>
        <file>Germain\DAYS OF THE NEWS\Days Of The New I\12-Cling.mp3</file>
      </files>
      <dates>
        <date>23/01/2017 19:51:17</date>
      </dates>
    </piece>
    <piece id="44186">
      <classement>
        <version date="14/06/2018 18:47:44" value="000000543.3" />
      </classement>
      <duration>122651</duration>
    </piece>
    <piece id="44187">
      <classement>
        <version date="14/06/2018 18:49:40" value="00000105.4" />
      </classement>
      <dates>
        <date>14/06/2018 18:49:47</date>
      </dates>
    </piece>
    <piece id="44189">
      <classement>
        <version date="14/06/2018 18:52:29" value="0000015.1" />
      </classement>
    </piece>
    <piece id="44243">
      <classement>
        <version date="14/06/2018 16:02:51" value="000000445.3" />
      </classement>
      <disabled />
    </piece>
    <piece id="44351">
      <classement>
        <version date="14/06/2018 16:43:48" value="00000055.2" />
      </classement>
    </piece>
    <piece id="44489">
      <classement>
        <version date="14/06/2018 18:26:41" value="000000514.3" />
      </classement>
      <disabled />
    </piece>
    <piece id="44536">
      <classement>
        <version date="14/06/2018 15:24:14" value="0000011.2" />
      </classement>
      <disabled />
    </piece>
    <piece id="44588">
      <classement>
        <version date="14/06/2018 17:30:17" value="000000222.4" />
      </classement>
      <disabled />
    </piece>
    <piece id="44655">
      <classement>
        <version date="14/06/2018 18:23:16" value="000000502.2" />
      </classement>
    </piece>
    <piece id="33144" deleted="true" />
    <piece id="33145" deleted="true" />
    <piece id="33146" deleted="true" />
    <piece id="33147" deleted="true" />
    <piece id="33148" deleted="true" />
    <piece id="33149" deleted="true" />
    <piece id="33150" deleted="true" />
    <piece id="33151" deleted="true" />
    <piece id="33152" deleted="true" />
    <piece id="33153" deleted="true" />
    <piece id="33155" deleted="true" />
    <piece id="44161" deleted="true" />
  </pieces>
</db>
