<?xml version="1.0" encoding="utf-8"?>
<db version="3" seq_piece="43679">
  <pieces>
    <piece id="4811" />
    <piece id="5422" />
    <piece id="5446" />
    <piece id="5464" />
    <piece id="5695" />
    <piece id="5716" />
    <piece id="5732" />
    <piece id="5956" />
    <piece id="6413" />
    <piece id="6425" />
    <piece id="6457" />
    <piece id="6608" />
    <piece id="6636" />
    <piece id="6773" />
    <piece id="7186" />
    <piece id="8055">
      <classement>
        <version date="07/05/2018 14:45:03" value="000002451.1" />
      </classement>
      <disabled />
    </piece>
    <piece id="9330" />
    <piece id="9370" />
    <piece id="9396">
      <classement>
        <version date="07/05/2018 12:03:09" value="000003452.3" />
      </classement>
    </piece>
    <piece id="9431" />
    <piece id="9432" />
    <piece id="9466" />
    <piece id="9515" />
    <piece id="9621" />
    <piece id="10173" />
    <piece id="10183">
      <classement>
        <version date="07/05/2018 14:50:02" value="0000042.1" />
      </classement>
      <disabled />
    </piece>
    <piece id="10422">
      <classement />
    </piece>
    <piece id="10613">
      <classement />
    </piece>
    <piece id="11253">
      <classement />
      <dates />
    </piece>
    <piece id="11913">
      <classement />
      <dates />
      <duration>155560</duration>
    </piece>
    <piece id="12064">
      <classement />
      <dates />
    </piece>
    <piece id="12329">
      <classement />
    </piece>
    <piece id="12398">
      <classement />
    </piece>
    <piece id="13899">
      <classement />
    </piece>
    <piece id="14225">
      <classement />
      <dates />
    </piece>
    <piece id="14243">
      <classement />
      <dates />
    </piece>
    <piece id="14420" />
    <piece id="14988">
      <classement />
    </piece>
    <piece id="15286">
      <classement>
        <version date="07/05/2018 18:06:15" value="000000532.4" />
      </classement>
      <disabled />
    </piece>
    <piece id="15503">
      <classement />
    </piece>
    <piece id="16354" />
    <piece id="16383">
      <classement />
    </piece>
    <piece id="16465">
      <classement>
        <version date="07/05/2018 17:49:34" value="000002551.4" />
      </classement>
    </piece>
    <piece id="16649">
      <classement />
      <dates />
    </piece>
    <piece id="16923">
      <dates />
    </piece>
    <piece id="17122">
      <classement>
        <version date="07/05/2018 14:15:21" value="00000345.3" />
      </classement>
      <disabled />
    </piece>
    <piece id="17151" />
    <piece id="17885">
      <classement>
        <version date="04/05/2018 16:24:10" value="000003435.3" />
      </classement>
    </piece>
    <piece id="18004">
      <classement>
        <version date="04/05/2018 17:01:34" value="000001002.4" />
      </classement>
      <disabled />
    </piece>
    <piece id="18018">
      <classement />
    </piece>
    <piece id="18038">
      <classement>
        <version date="07/05/2018 14:40:27" value="000002504.1" />
      </classement>
      <disabled />
    </piece>
    <piece id="18083" />
    <piece id="18219">
      <classement>
        <version date="07/05/2018 18:11:32" value="000003155.3" />
      </classement>
    </piece>
    <piece id="18516">
      <classement>
        <version date="07/05/2018 14:55:01" value="000002402.2" />
      </classement>
      <disabled />
    </piece>
    <piece id="18530">
      <classement>
        <version date="07/05/2018 15:55:30" value="00000432.2" />
      </classement>
    </piece>
    <piece id="18543">
      <classement>
        <version date="07/05/2018 17:48:07" value="000003504.3" />
      </classement>
    </piece>
    <piece id="18547" />
    <piece id="18684">
      <classement>
        <version date="07/05/2018 15:58:22" value="000003542.3" />
      </classement>
    </piece>
    <piece id="18905">
      <classement>
        <version date="07/05/2018 18:16:17" value="000002452.1" />
      </classement>
      <disabled />
    </piece>
    <piece id="18955">
      <classement>
        <version date="07/05/2018 14:41:42" value="0000025132.3" />
      </classement>
    </piece>
    <piece id="19068" />
    <piece id="19071">
      <classement>
        <version date="07/05/2018 12:02:23" value="000002354.5" />
      </classement>
      <dates>
        <date>07/05/2018 12:01:55</date>
      </dates>
    </piece>
    <piece id="19072" />
    <piece id="19073" />
    <piece id="19075">
      <classement>
        <version date="07/05/2018 14:16:47" value="000002513.1" />
      </classement>
      <disabled />
    </piece>
    <piece id="19096">
      <classement>
        <version date="07/05/2018 14:18:01" value="000003035.3" />
      </classement>
      <disabled />
    </piece>
    <piece id="19315" />
    <piece id="19806">
      <classement>
        <version date="07/05/2018 11:36:21" value="000002422.2" />
      </classement>
    </piece>
    <piece id="19932">
      <files>
        <file>Ipod\noir\F03\RTED.m4a</file>
      </files>
    </piece>
    <piece id="19933">
      <files>
        <file>Ipod\noir\F12\JYSP.m4a</file>
      </files>
    </piece>
    <piece id="19934">
      <files>
        <file>Ipod\noir\F13\PRDP.m4a</file>
      </files>
    </piece>
    <piece id="19935">
      <files>
        <file>Ipod\noir\F04\UXOU.m4a</file>
      </files>
    </piece>
    <piece id="42743" parent="19935" />
    <piece id="19936">
      <files>
        <file>Ipod\noir\F12\MKCI.m4a</file>
      </files>
    </piece>
    <piece id="19937">
      <files>
        <file>Ipod\noir\F06\SVKN.m4a</file>
      </files>
    </piece>
    <piece id="19938">
      <files>
        <file>Ipod\noir\F07\XJUF.m4a</file>
      </files>
    </piece>
    <piece id="19940">
      <files>
        <file>Ipod\noir\F05\IZSL.m4a</file>
      </files>
    </piece>
    <piece id="19942">
      <files>
        <file>Ipod\noir\F13\ILFD.m4a</file>
      </files>
    </piece>
    <piece id="19943">
      <files>
        <file>Ipod\noir\F06\HRZP.m4a</file>
      </files>
    </piece>
    <piece id="19944">
      <files>
        <file>Ipod\noir\F06\MOAQ.m4a</file>
      </files>
    </piece>
    <piece id="19945">
      <files>
        <file>Ipod\noir\F01\VYKP.m4a</file>
      </files>
    </piece>
    <piece id="20247">
      <classement>
        <version date="07/05/2018 17:46:46" value="0000025224.3" />
      </classement>
    </piece>
    <piece id="20340">
      <classement>
        <version date="07/05/2018 14:43:58" value="000003042.1" />
      </classement>
    </piece>
    <piece id="20347">
      <classement>
        <version date="07/05/2018 11:56:51" value="000002332.4" />
      </classement>
      <disabled />
    </piece>
    <piece id="20922">
      <classement>
        <version date="07/05/2018 14:57:02" value="000003011.3" />
      </classement>
      <disabled />
    </piece>
    <piece id="21247">
      <classement>
        <version date="07/05/2018 15:00:36" value="000003304.3" />
      </classement>
    </piece>
    <piece id="21320">
      <classement>
        <version date="07/05/2018 14:36:40" value="000002344.4" />
      </classement>
      <disabled />
    </piece>
    <piece id="21572">
      <dates />
    </piece>
    <piece id="21781">
      <classement>
        <version date="07/05/2018 11:41:18" value="000003012.4" />
      </classement>
    </piece>
    <piece id="22013">
      <classement>
        <version date="07/05/2018 16:05:03" value="000002324.2" />
      </classement>
      <disabled />
    </piece>
    <piece id="22209">
      <classement>
        <version date="04/05/2018 16:33:36" value="000002235.4" />
      </classement>
      <disabled />
    </piece>
    <piece id="22385">
      <classement>
        <version date="04/05/2018 16:20:12" value="0000024432.1" />
      </classement>
    </piece>
    <piece id="22393">
      <classement>
        <version date="04/05/2018 16:56:45" value="000001224.2" />
      </classement>
      <disabled />
    </piece>
    <piece id="22600">
      <classement>
        <version date="07/05/2018 11:54:01" value="0000025122.3" />
      </classement>
    </piece>
    <piece id="22789">
      <classement>
        <version date="07/05/2018 17:42:50" value="000002454.1" />
      </classement>
      <disabled />
    </piece>
    <piece id="22949">
      <classement>
        <version date="07/05/2018 18:14:37" value="000004033.3" />
      </classement>
    </piece>
    <piece id="23060">
      <classement>
        <version date="07/05/2018 14:59:33" value="0000024534.3" />
      </classement>
    </piece>
    <piece id="23238">
      <classement>
        <version date="07/05/2018 11:53:01" value="000002312.4" />
      </classement>
      <disabled />
    </piece>
    <piece id="23355">
      <classement>
        <version date="04/05/2018 16:08:55" value="000002350.4" />
      </classement>
      <disabled />
    </piece>
    <piece id="23538">
      <classement>
        <version date="07/05/2018 16:07:04" value="000003020.1" />
      </classement>
      <disabled />
    </piece>
    <piece id="23666">
      <classement>
        <version date="04/05/2018 16:47:36" value="000003034.3" />
      </classement>
      <disabled />
    </piece>
    <piece id="24333">
      <dates />
    </piece>
    <piece id="24344">
      <dates />
    </piece>
    <piece id="24447">
      <classement />
      <dates />
    </piece>
    <piece id="24912">
      <classement />
    </piece>
    <piece id="25427">
      <classement />
    </piece>
    <piece id="25946" />
    <piece id="26534">
      <classement />
    </piece>
    <piece id="26579">
      <dates />
    </piece>
    <piece id="26691">
      <classement />
      <dates />
    </piece>
    <piece id="26725">
      <classement />
      <dates />
    </piece>
    <piece id="26778">
      <classement />
      <dates />
    </piece>
    <piece id="26811">
      <classement />
      <dates />
    </piece>
    <piece id="26948">
      <classement>
        <version date="07/05/2018 11:44:03" value="00000315.2" />
      </classement>
      <disabled />
    </piece>
    <piece id="26972">
      <classement>
        <version date="07/05/2018 11:57:35" value="000003532.3" />
      </classement>
    </piece>
    <piece id="27415">
      <classement>
        <version date="07/05/2018 11:51:12" value="000003411.2" />
      </classement>
    </piece>
    <piece id="27737">
      <classement />
    </piece>
    <piece id="28125">
      <classement>
        <version date="07/05/2018 18:09:11" value="000002541.2" />
      </classement>
      <dates>
        <date>07/05/2018 18:08:53</date>
      </dates>
    </piece>
    <piece id="28341">
      <classement>
        <version date="04/05/2018 16:22:17" value="000003434.3" />
      </classement>
    </piece>
    <piece id="29023">
      <classement>
        <version date="07/05/2018 14:51:19" value="0000025212.3" />
      </classement>
    </piece>
    <piece id="29163" />
    <piece id="29344">
      <classement />
      <dates />
    </piece>
    <piece id="29470">
      <classement>
        <version date="07/05/2018 14:47:32" value="000003335.3" />
      </classement>
      <dates>
        <date>07/05/2018 14:46:41</date>
      </dates>
    </piece>
    <piece id="29526">
      <classement>
        <version date="07/05/2018 11:59:34" value="000003202.2" />
      </classement>
    </piece>
    <piece id="29542">
      <classement>
        <version date="04/05/2018 16:44:08" value="00000314.4" />
      </classement>
      <disabled />
    </piece>
    <piece id="29710">
      <classement />
    </piece>
    <piece id="29879">
      <classement>
        <version date="04/05/2018 16:40:13" value="00000423.2" />
      </classement>
    </piece>
    <piece id="30384">
      <classement>
        <version date="07/05/2018 11:40:19" value="000003405.3" />
      </classement>
    </piece>
    <piece id="30422">
      <dates />
    </piece>
    <piece id="31040">
      <classement />
      <dates />
    </piece>
    <piece id="31526">
      <classement>
        <version date="04/05/2018 16:19:04" value="000002430.4" />
      </classement>
      <disabled />
    </piece>
    <piece id="31840">
      <classement>
        <version date="07/05/2018 15:59:56" value="000003313.3" />
      </classement>
    </piece>
    <piece id="32062">
      <classement />
      <dates />
    </piece>
    <piece id="32102">
      <classement />
    </piece>
    <piece id="32117">
      <classement />
      <dates />
    </piece>
    <piece id="32532">
      <classement>
        <version date="07/05/2018 14:14:12" value="000003455.3" />
      </classement>
    </piece>
    <piece id="32596">
      <classement>
        <version date="07/05/2018 14:32:24" value="000002522.1" />
      </classement>
      <disabled />
    </piece>
    <piece id="32740">
      <classement />
      <duration>195896</duration>
    </piece>
    <piece id="33050" />
    <piece id="33093">
      <classement>
        <version date="04/05/2018 16:30:13" value="000003111.2" />
      </classement>
    </piece>
    <piece id="33312" />
    <piece id="33313" />
    <piece id="33314" />
    <piece id="33322">
      <classement>
        <version date="07/05/2018 16:09:47" value="000001525.2" />
      </classement>
      <disabled />
    </piece>
    <piece id="33349">
      <classement>
        <version date="07/05/2018 14:37:44" value="000001351.2" />
      </classement>
      <disabled />
    </piece>
    <piece id="33465">
      <classement>
        <version date="04/05/2018 16:53:59" value="000002245.4" />
      </classement>
      <disabled />
    </piece>
    <piece id="33819">
      <classement>
        <version date="07/05/2018 18:01:42" value="000002033.2" />
      </classement>
      <disabled />
    </piece>
    <piece id="36687">
      <classement />
      <dates />
    </piece>
    <piece id="36850">
      <classement />
      <dates />
    </piece>
    <piece id="38104">
      <dates />
    </piece>
    <piece id="38477">
      <classement />
      <dates />
    </piece>
    <piece id="40003">
      <classement>
        <version date="07/05/2018 11:48:49" value="00102.3" />
      </classement>
    </piece>
    <piece id="40373">
      <dates />
    </piece>
    <piece id="40469">
      <classement />
      <dates />
    </piece>
    <piece id="40499">
      <classement>
        <version date="07/05/2018 17:52:34" value="000003013.1" />
      </classement>
      <dates>
        <date>07/05/2018 17:55:03</date>
      </dates>
      <disabled />
    </piece>
    <piece id="40505">
      <classement>
        <version date="04/05/2018 16:28:13" value="000120.1" />
      </classement>
    </piece>
    <piece id="40843">
      <classement>
        <version date="04/05/2018 16:59:05" />
      </classement>
      <disabled />
    </piece>
    <piece id="40844">
      <classement>
        <version date="07/05/2018 11:45:05" value="0000311.3" />
      </classement>
    </piece>
    <piece id="41026">
      <classement>
        <version date="07/05/2018 11:39:07" value="000041.5" />
      </classement>
    </piece>
    <piece id="41059">
      <classement>
        <version date="07/05/2018 14:13:13" value="000042.5" />
      </classement>
    </piece>
    <piece id="41269" />
    <piece id="41293" />
    <piece id="41297" />
    <piece id="41343" />
    <piece id="41344" />
    <piece id="41385" />
    <piece id="41426" />
    <piece id="41436" />
    <piece id="41452">
      <classement>
        <version date="07/05/2018 18:12:58" value="000003133.3" />
      </classement>
      <disabled />
    </piece>
    <piece id="41470" />
    <piece id="41471" />
    <piece id="41472" />
    <piece id="41477" />
    <piece id="41489">
      <classement>
        <version date="04/05/2018 16:32:16" value="000002353.4" />
      </classement>
      <disabled />
    </piece>
    <piece id="41506" />
    <piece id="41515" />
    <piece id="41520">
      <classement />
    </piece>
    <piece id="41547" />
    <piece id="41554">
      <classement>
        <version date="04/05/2018 17:00:29" value="000003302.2" />
      </classement>
    </piece>
    <piece id="41561" />
    <piece id="41569">
      <classement>
        <version date="07/05/2018 18:04:53" value="0000025232.3" />
      </classement>
    </piece>
    <piece id="41576" />
    <piece id="41583" />
    <piece id="41601" />
    <piece id="41605">
      <classement />
    </piece>
    <piece id="41606" />
    <piece id="41610" />
    <piece id="41620" />
    <piece id="41621">
      <classement>
        <version date="04/05/2018 16:52:53" value="00000322.4" />
      </classement>
      <disabled />
    </piece>
    <piece id="41625" />
    <piece id="41637" />
    <piece id="41658">
      <classement>
        <version date="07/05/2018 17:40:19" value="000002351.4" />
      </classement>
      <dates>
        <date>07/05/2018 17:39:31</date>
      </dates>
      <disabled />
    </piece>
    <piece id="41702" />
    <piece id="41716">
      <classement>
        <version date="04/05/2018 16:39:01" value="000003221.2" />
      </classement>
      <dates>
        <date>04/05/2018 16:37:37</date>
      </dates>
    </piece>
    <piece id="41723" />
    <piece id="41757" />
    <piece id="41819" />
    <piece id="41841" />
    <piece id="41891" />
    <piece id="41912" />
    <piece id="41925" />
    <piece id="41932">
      <classement />
      <dates />
    </piece>
    <piece id="41934">
      <classement>
        <version date="07/05/2018 15:56:32" value="000002440.4" />
      </classement>
      <disabled />
    </piece>
    <piece id="41942" />
    <piece id="41943" />
    <piece id="41982" />
    <piece id="42001" />
    <piece id="42042" />
    <piece id="42055" />
    <piece id="42100" />
    <piece id="42123">
      <dates />
    </piece>
    <piece id="42137">
      <classement>
        <version date="07/05/2018 11:46:14" value="000002553.4" />
      </classement>
    </piece>
    <piece id="42142">
      <classement>
        <version date="07/05/2018 11:37:45" value="000003312.2" />
      </classement>
    </piece>
    <piece id="42150" />
    <piece id="42173" />
    <piece id="42181" />
    <piece id="42186">
      <classement />
    </piece>
    <piece id="42224" />
    <piece id="42241">
      <classement />
    </piece>
    <piece id="42245">
      <classement>
        <version date="07/05/2018 11:58:35" value="000002433.4" />
      </classement>
      <disabled />
    </piece>
    <piece id="42246" />
    <piece id="42247" />
    <piece id="42248" />
    <piece id="42267" />
    <piece id="42277">
      <classement>
        <version date="07/05/2018 14:48:44" value="000003541.3" />
      </classement>
    </piece>
    <piece id="42302" />
    <piece id="42313">
      <classement>
        <version date="04/05/2018 16:26:43" value="0000303.3" />
      </classement>
    </piece>
    <piece id="42319" />
    <piece id="42338" />
    <piece id="42340" />
    <piece id="42362">
      <classement>
        <version date="04/05/2018 17:22:39" value="000003113.2" />
      </classement>
    </piece>
    <piece id="42392" />
    <piece id="42540" />
    <piece id="42578" />
    <piece id="42666" />
    <piece id="42707" />
    <piece id="42722" />
    <piece id="42841" />
    <piece id="42860" />
    <piece id="42869">
      <classement>
        <version date="04/05/2018 16:54:56" value="000002543.1" />
      </classement>
      <disabled />
    </piece>
    <piece id="42936" />
    <piece id="42938" />
    <piece id="42963" />
    <piece id="42973" />
    <piece id="42980" />
    <piece id="43012" />
    <piece id="43029" />
    <piece id="43038" />
    <piece id="43071" />
    <piece id="43073" />
    <piece id="43088" />
    <piece id="43091">
      <classement>
        <version date="07/05/2018 15:54:32" value="000002534.1" />
      </classement>
      <disabled />
    </piece>
    <piece id="43106" />
    <piece id="43111" />
    <piece id="43136" />
    <piece id="43142" />
    <piece id="43170" />
    <piece id="43186">
      <dates>
        <date>07/05/2018 14:20:55</date>
      </dates>
    </piece>
    <piece id="43188" />
    <piece id="43191" />
    <piece id="43207" />
    <piece id="43270" />
    <piece id="43317" />
    <piece id="43330" />
    <piece id="43359" />
    <piece id="43398" />
    <piece id="43406" />
    <piece id="43426" />
    <piece id="43455">
      <classement>
        <version date="04/05/2018 16:51:37" value="000003444.3" />
      </classement>
      <dates>
        <date>04/05/2018 16:50:44</date>
      </dates>
    </piece>
    <piece id="43485" />
    <piece id="43575" />
    <piece id="43634" />
    <piece id="43676" />
    <piece id="42449" deleted="true" />
    <piece id="42640" deleted="true" />
    <piece id="42798" deleted="true" />
    <piece id="42906" deleted="true" />
    <piece id="42926" deleted="true" />
    <piece id="42957" deleted="true" />
    <piece id="43079" deleted="true" />
    <piece id="43553" deleted="true" />
    <piece id="43563" deleted="true" />
    <piece id="43626" deleted="true" />
    <piece id="43654" deleted="true" />
  </pieces>
</db>
